{
  "data": [
    {
      "winner_id": 1454782,
      "loser_id": 3077694,
      "winner_score": 3,
      "loser_score": 1,
      "round_text": "Winners Final",
      "round": 4,
      "phase": "1",
      "wave": null,
      "dq": false,
      "cancel": false,
      "state": 3,
      "details": []
    },
    {
      "winner_id": 3077694,
      "loser_id": 3082564,
      "winner_score": 3,
      "loser_score": 0,
      "round_text": "Winners Semi-Final",
      "round": 3,
      "phase": "1",
      "wave": null,
      "dq": false,
      "cancel": false,
      "state": 3,
      "details": []
    },
    {
      "winner_id": 1454782,
      "loser_id": 3053860,
      "winner_score": 3,
      "loser_score": 1,
      "round_text": "Winners Semi-Final",
      "round": 3,
      "phase": "1",
      "wave": null,
      "dq": false,
      "cancel": false,
      "state": 3,
      "details": []
    },
    {
      "winner_id": 3082564,
      "loser_id": 355880,
      "winner_score": 2,
      "loser_score": 1,
      "round_text": "Losers Quarter-Final",
      "round": -6,
      "phase": "1",
      "wave": null,
      "dq": false,
      "cancel": false,
      "state": 3,
      "details": []
    },
    {
      "winner_id": 3053860,
      "loser_id": 3069539,
      "winner_score": 2,
      "loser_score": 0,
      "round_text": "Losers Quarter-Final",
      "round": -6,
      "phase": "1",
      "wave": null,
      "dq": false,
      "cancel": false,
      "state": 3,
      "details": []
    },
    {
      "winner_id": 355880,
      "loser_id": 1825446,
      "winner_score": 2,
      "loser_score": 1,
      "round_text": "Losers Round 3",
      "round": -5,
      "phase": "1",
      "wave": null,
      "dq": false,
      "cancel": false,
      "state": 3,
      "details": []
    },
    {
      "winner_id": 3069539,
      "loser_id": 2101338,
      "winner_score": 2,
      "loser_score": 0,
      "round_text": "Losers Round 3",
      "round": -5,
      "phase": "1",
      "wave": null,
      "dq": false,
      "cancel": false,
      "state": 3,
      "details": []
    },
    {
      "winner_id": 3082564,
      "loser_id": 2346479,
      "winner_score": 0,
      "loser_score": -1,
      "round_text": "Winners Quarter-Final",
      "round": 2,
      "phase": "1",
      "wave": null,
      "dq": true,
      "cancel": false,
      "state": 3,
      "details": []
    },
    {
      "winner_id": 3077694,
      "loser_id": 3069539,
      "winner_score": 2,
      "loser_score": 0,
      "round_text": "Winners Quarter-Final",
      "round": 2,
      "phase": "1",
      "wave": null,
      "dq": false,
      "cancel": false,
      "state": 3,
      "details": []
    },
    {
      "winner_id": 1454782,
      "loser_id": 355880,
      "winner_score": 2,
      "loser_score": 0,
      "round_text": "Winners Quarter-Final",
      "round": 2,
      "phase": "1",
      "wave": null,
      "dq": false,
      "cancel": false,
      "state": 3,
      "details": []
    },
    {
      "winner_id": 3053860,
      "loser_id": 1878279,
      "winner_score": 2,
      "loser_score": 0,
      "round_text": "Winners Quarter-Final",
      "round": 2,
      "phase": "1",
      "wave": null,
      "dq": false,
      "cancel": false,
      "state": 3,
      "details": []
    },
    {
      "winner_id": 1825446,
      "loser_id": 1878279,
      "winner_score": 2,
      "loser_score": 1,
      "round_text": "Losers Round 2",
      "round": -4,
      "phase": "1",
      "wave": null,
      "dq": false,
      "cancel": false,
      "state": 3,
      "details": []
    },
    {
      "winner_id": 355880,
      "loser_id": 2803676,
      "winner_score": 2,
      "loser_score": 0,
      "round_text": "Losers Round 2",
      "round": -4,
      "phase": "1",
      "wave": null,
      "dq": false,
      "cancel": false,
      "state": 3,
      "details": []
    },
    {
      "winner_id": 3069539,
      "loser_id": 3383091,
      "winner_score": 2,
      "loser_score": 1,
      "round_text": "Losers Round 2",
      "round": -4,
      "phase": "1",
      "wave": null,
      "dq": false,
      "cancel": false,
      "state": 3,
      "details": []
    },
    {
      "winner_id": 2101338,
      "loser_id": 2346479,
      "winner_score": 0,
      "loser_score": -1,
      "round_text": "Losers Round 2",
      "round": -4,
      "phase": "1",
      "wave": null,
      "dq": true,
      "cancel": false,
      "state": 3,
      "details": []
    },
    {
      "winner_id": 2803676,
      "loser_id": 3077614,
      "winner_score": 2,
      "loser_score": 1,
      "round_text": "Losers Round 1",
      "round": -3,
      "phase": "1",
      "wave": null,
      "dq": false,
      "cancel": false,
      "state": 3,
      "details": []
    },
    {
      "winner_id": 2101338,
      "loser_id": 1937072,
      "winner_score": 2,
      "loser_score": 0,
      "round_text": "Losers Round 1",
      "round": -3,
      "phase": "1",
      "wave": null,
      "dq": false,
      "cancel": false,
      "state": 3,
      "details": []
    },
    {
      "winner_id": 3082564,
      "loser_id": 1825446,
      "winner_score": 2,
      "loser_score": 1,
      "round_text": "Winners Round 1",
      "round": 1,
      "phase": "1",
      "wave": null,
      "dq": false,
      "cancel": false,
      "state": 3,
      "details": []
    },
    {
      "winner_id": 3077694,
      "loser_id": 3077614,
      "winner_score": 2,
      "loser_score": 0,
      "round_text": "Winners Round 1",
      "round": 1,
      "phase": "1",
      "wave": null,
      "dq": false,
      "cancel": false,
      "state": 3,
      "details": []
    },
    {
      "winner_id": 3069539,
      "loser_id": 2803676,
      "winner_score": 2,
      "loser_score": 0,
      "round_text": "Winners Round 1",
      "round": 1,
      "phase": "1",
      "wave": null,
      "dq": false,
      "cancel": false,
      "state": 3,
      "details": []
    },
    {
      "winner_id": 355880,
      "loser_id": 3383091,
      "winner_score": 2,
      "loser_score": 0,
      "round_text": "Winners Round 1",
      "round": 1,
      "phase": "1",
      "wave": null,
      "dq": false,
      "cancel": false,
      "state": 3,
      "details": []
    },
    {
      "winner_id": 3053860,
      "loser_id": 2101338,
      "winner_score": 2,
      "loser_score": 0,
      "round_text": "Winners Round 1",
      "round": 1,
      "phase": "1",
      "wave": null,
      "dq": false,
      "cancel": false,
      "state": 3,
      "details": []
    },
    {
      "winner_id": 1878279,
      "loser_id": 1937072,
      "winner_score": 2,
      "loser_score": 1,
      "round_text": "Winners Round 1",
      "round": 1,
      "phase": "1",
      "wave": null,
      "dq": false,
      "cancel": false,
      "state": 3,
      "details": []
    },
    {
      "winner_id": 3053860,
      "loser_id": 3082564,
      "winner_score": 0,
      "loser_score": 0,
      "round_text": "Losers Semi-Final",
      "round": -7,
      "phase": "1",
      "wave": null,
      "dq": false,
      "cancel": true,
      "state": 1,
      "details": []
    }
  ],
  "version": "1.0"
}