{
  "data": [
    {
      "winner_id": 2086172,
      "loser_id": 1918910,
      "winner_score": 3,
      "loser_score": 0,
      "round_text": "Grand Final",
      "round": 5,
      "phase": "1",
      "wave": null,
      "dq": false,
      "cancel": false,
      "state": 3,
      "details": []
    },
    {
      "winner_id": 2086172,
      "loser_id": 1918910,
      "winner_score": 3,
      "loser_score": 0,
      "round_text": "Winners Final",
      "round": 4,
      "phase": "1",
      "wave": null,
      "dq": false,
      "cancel": false,
      "state": 3,
      "details": [
        {
          "game_id": 39029845,
          "order_num": 1,
          "winner_id": 2086172,
          "entrant1_score": null,
          "entrant2_score": null,
          "stage": null,
          "selections": [
            {
              "user_id": 1918910,
              "selection_id": 58305782,
              "character_id": 1747,
              "character_name": "Min Min"
            },
            {
              "user_id": 2086172,
              "selection_id": 58305783,
              "character_id": 1333,
              "character_name": "Toon Link"
            }
          ]
        },
        {
          "game_id": 39029846,
          "order_num": 2,
          "winner_id": 2086172,
          "entrant1_score": null,
          "entrant2_score": null,
          "stage": null,
          "selections": [
            {
              "user_id": 1918910,
              "selection_id": 58305784,
              "character_id": 1747,
              "character_name": "Min Min"
            },
            {
              "user_id": 2086172,
              "selection_id": 58305785,
              "character_id": 1333,
              "character_name": "Toon Link"
            }
          ]
        },
        {
          "game_id": 39029847,
          "order_num": 3,
          "winner_id": 2086172,
          "entrant1_score": null,
          "entrant2_score": null,
          "stage": null,
          "selections": [
            {
              "user_id": 1918910,
              "selection_id": 58305786,
              "character_id": 1795,
              "character_name": "Pyra & Mythra"
            },
            {
              "user_id": 2086172,
              "selection_id": 58305787,
              "character_id": 1333,
              "character_name": "Toon Link"
            }
          ]
        }
      ]
    },
    {
      "winner_id": 1918910,
      "loser_id": 2053290,
      "winner_score": 2,
      "loser_score": 1,
      "round_text": "Losers Final",
      "round": -8,
      "phase": "1",
      "wave": null,
      "dq": false,
      "cancel": false,
      "state": 3,
      "details": [
        {
          "game_id": 39029873,
          "order_num": 1,
          "winner_id": 2053290,
          "entrant1_score": 0,
          "entrant2_score": null,
          "stage": null,
          "selections": [
            {
              "user_id": 1918910,
              "selection_id": 58305838,
              "character_id": 1747,
              "character_name": "Min Min"
            },
            {
              "user_id": 2053290,
              "selection_id": 58305839,
              "character_id": 1846,
              "character_name": "Kazuya"
            }
          ]
        },
        {
          "game_id": 39029874,
          "order_num": 2,
          "winner_id": 1918910,
          "entrant1_score": null,
          "entrant2_score": 0,
          "stage": null,
          "selections": [
            {
              "user_id": 1918910,
              "selection_id": 58305840,
              "character_id": 1747,
              "character_name": "Min Min"
            },
            {
              "user_id": 2053290,
              "selection_id": 58305841,
              "character_id": 1846,
              "character_name": "Kazuya"
            }
          ]
        },
        {
          "game_id": 39029875,
          "order_num": 3,
          "winner_id": 1918910,
          "entrant1_score": null,
          "entrant2_score": 0,
          "stage": null,
          "selections": [
            {
              "user_id": 1918910,
              "selection_id": 58305842,
              "character_id": 1747,
              "character_name": "Min Min"
            },
            {
              "user_id": 2053290,
              "selection_id": 58305843,
              "character_id": 1846,
              "character_name": "Kazuya"
            }
          ]
        }
      ]
    },
    {
      "winner_id": 2053290,
      "loser_id": 383771,
      "winner_score": 2,
      "loser_score": 0,
      "round_text": "Losers Semi-Final",
      "round": -7,
      "phase": "1",
      "wave": null,
      "dq": false,
      "cancel": false,
      "state": 3,
      "details": [
        {
          "game_id": 39029869,
          "order_num": 1,
          "winner_id": 2053290,
          "entrant1_score": null,
          "entrant2_score": null,
          "stage": null,
          "selections": [
            {
              "user_id": 383771,
              "selection_id": 58305830,
              "character_id": 1300,
              "character_name": "Lucina"
            },
            {
              "user_id": 2053290,
              "selection_id": 58305831,
              "character_id": 1846,
              "character_name": "Kazuya"
            }
          ]
        },
        {
          "game_id": 39029870,
          "order_num": 2,
          "winner_id": 2053290,
          "entrant1_score": null,
          "entrant2_score": null,
          "stage": null,
          "selections": [
            {
              "user_id": 383771,
              "selection_id": 58305832,
              "character_id": 1300,
              "character_name": "Lucina"
            },
            {
              "user_id": 2053290,
              "selection_id": 58305833,
              "character_id": 1846,
              "character_name": "Kazuya"
            }
          ]
        }
      ]
    },
    {
      "winner_id": 2086172,
      "loser_id": 2053290,
      "winner_score": 3,
      "loser_score": 1,
      "round_text": "Winners Semi-Final",
      "round": 3,
      "phase": "1",
      "wave": null,
      "dq": false,
      "cancel": false,
      "state": 3,
      "details": [
        {
          "game_id": 39029688,
          "order_num": 1,
          "winner_id": 2086172,
          "entrant1_score": null,
          "entrant2_score": 0,
          "stage": null,
          "selections": [
            {
              "user_id": 2086172,
              "selection_id": 58305468,
              "character_id": 1333,
              "character_name": "Toon Link"
            },
            {
              "user_id": 2053290,
              "selection_id": 58305469,
              "character_id": 1846,
              "character_name": "Kazuya"
            }
          ]
        },
        {
          "game_id": 39029689,
          "order_num": 2,
          "winner_id": 2086172,
          "entrant1_score": null,
          "entrant2_score": 0,
          "stage": null,
          "selections": [
            {
              "user_id": 2086172,
              "selection_id": 58305470,
              "character_id": 1333,
              "character_name": "Toon Link"
            },
            {
              "user_id": 2053290,
              "selection_id": 58305471,
              "character_id": 1846,
              "character_name": "Kazuya"
            }
          ]
        },
        {
          "game_id": 39029690,
          "order_num": 3,
          "winner_id": 2053290,
          "entrant1_score": 0,
          "entrant2_score": null,
          "stage": null,
          "selections": [
            {
              "user_id": 2086172,
              "selection_id": 58305472,
              "character_id": 1333,
              "character_name": "Toon Link"
            },
            {
              "user_id": 2053290,
              "selection_id": 58305473,
              "character_id": 1410,
              "character_name": "Ken"
            }
          ]
        },
        {
          "game_id": 39029691,
          "order_num": 4,
          "winner_id": 2086172,
          "entrant1_score": 0,
          "entrant2_score": 0,
          "stage": null,
          "selections": [
            {
              "user_id": 2086172,
              "selection_id": 58305474,
              "character_id": 1333,
              "character_name": "Toon Link"
            },
            {
              "user_id": 2053290,
              "selection_id": 58305475,
              "character_id": 1410,
              "character_name": "Ken"
            }
          ]
        }
      ]
    },
    {
      "winner_id": 1918910,
      "loser_id": 1844513,
      "winner_score": 3,
      "loser_score": 2,
      "round_text": "Winners Semi-Final",
      "round": 3,
      "phase": "1",
      "wave": null,
      "dq": false,
      "cancel": false,
      "state": 3,
      "details": []
    },
    {
      "winner_id": 2053290,
      "loser_id": 1453340,
      "winner_score": 2,
      "loser_score": 1,
      "round_text": "Losers Quarter-Final",
      "round": -6,
      "phase": "1",
      "wave": null,
      "dq": false,
      "cancel": false,
      "state": 3,
      "details": [
        {
          "game_id": 39029863,
          "order_num": 1,
          "winner_id": 2053290,
          "entrant1_score": 0,
          "entrant2_score": 0,
          "stage": null,
          "selections": [
            {
              "user_id": 1453340,
              "selection_id": 58305818,
              "character_id": 1326,
              "character_name": "Roy"
            },
            {
              "user_id": 2053290,
              "selection_id": 58305819,
              "character_id": 1846,
              "character_name": "Kazuya"
            }
          ]
        },
        {
          "game_id": 39029864,
          "order_num": 2,
          "winner_id": 1453340,
          "entrant1_score": 0,
          "entrant2_score": null,
          "stage": null,
          "selections": [
            {
              "user_id": 1453340,
              "selection_id": 58305820,
              "character_id": 1326,
              "character_name": "Roy"
            },
            {
              "user_id": 2053290,
              "selection_id": 58305821,
              "character_id": 1846,
              "character_name": "Kazuya"
            }
          ]
        },
        {
          "game_id": 39029865,
          "order_num": 3,
          "winner_id": 2053290,
          "entrant1_score": null,
          "entrant2_score": 0,
          "stage": null,
          "selections": [
            {
              "user_id": 1453340,
              "selection_id": 58305822,
              "character_id": 1326,
              "character_name": "Roy"
            },
            {
              "user_id": 2053290,
              "selection_id": 58305823,
              "character_id": 1846,
              "character_name": "Kazuya"
            }
          ]
        }
      ]
    },
    {
      "winner_id": 383771,
      "loser_id": 1844513,
      "winner_score": 2,
      "loser_score": 1,
      "round_text": "Losers Quarter-Final",
      "round": -6,
      "phase": "1",
      "wave": null,
      "dq": false,
      "cancel": false,
      "state": 3,
      "details": [
        {
          "game_id": 39029853,
          "order_num": 1,
          "winner_id": 1844513,
          "entrant1_score": null,
          "entrant2_score": 0,
          "stage": null,
          "selections": [
            {
              "user_id": 1844513,
              "selection_id": 58305798,
              "character_id": 1328,
              "character_name": "Samus"
            },
            {
              "user_id": 383771,
              "selection_id": 58305799,
              "character_id": 1300,
              "character_name": "Lucina"
            }
          ]
        },
        {
          "game_id": 39029854,
          "order_num": 2,
          "winner_id": 383771,
          "entrant1_score": 0,
          "entrant2_score": null,
          "stage": null,
          "selections": [
            {
              "user_id": 1844513,
              "selection_id": 58305800,
              "character_id": 1328,
              "character_name": "Samus"
            },
            {
              "user_id": 383771,
              "selection_id": 58305801,
              "character_id": 1300,
              "character_name": "Lucina"
            }
          ]
        },
        {
          "game_id": 39029855,
          "order_num": 3,
          "winner_id": 383771,
          "entrant1_score": 0,
          "entrant2_score": null,
          "stage": null,
          "selections": [
            {
              "user_id": 1844513,
              "selection_id": 58305802,
              "character_id": 1328,
              "character_name": "Samus"
            },
            {
              "user_id": 383771,
              "selection_id": 58305803,
              "character_id": 1300,
              "character_name": "Lucina"
            }
          ]
        }
      ]
    },
    {
      "winner_id": 1453340,
      "loser_id": 837458,
      "winner_score": 2,
      "loser_score": 0,
      "round_text": "Losers Round 3",
      "round": -5,
      "phase": "1",
      "wave": null,
      "dq": false,
      "cancel": false,
      "state": 3,
      "details": []
    },
    {
      "winner_id": 383771,
      "loser_id": 3031255,
      "winner_score": 2,
      "loser_score": 1,
      "round_text": "Losers Round 3",
      "round": -5,
      "phase": "1",
      "wave": null,
      "dq": false,
      "cancel": false,
      "state": 3,
      "details": []
    },
    {
      "winner_id": 2086172,
      "loser_id": 2515351,
      "winner_score": 2,
      "loser_score": 0,
      "round_text": "Winners Quarter-Final",
      "round": 2,
      "phase": "1",
      "wave": null,
      "dq": false,
      "cancel": false,
      "state": 3,
      "details": [
        {
          "game_id": 39029345,
          "order_num": 1,
          "winner_id": 2086172,
          "entrant1_score": null,
          "entrant2_score": null,
          "stage": null,
          "selections": [
            {
              "user_id": 2086172,
              "selection_id": 58304799,
              "character_id": 1333,
              "character_name": "Toon Link"
            },
            {
              "user_id": 2515351,
              "selection_id": 58304800,
              "character_id": 1273,
              "character_name": "Bowser"
            }
          ]
        },
        {
          "game_id": 39029346,
          "order_num": 2,
          "winner_id": 2086172,
          "entrant1_score": null,
          "entrant2_score": null,
          "stage": null,
          "selections": [
            {
              "user_id": 2086172,
              "selection_id": 58304801,
              "character_id": 1333,
              "character_name": "Toon Link"
            },
            {
              "user_id": 2515351,
              "selection_id": 58304802,
              "character_id": 1273,
              "character_name": "Bowser"
            }
          ]
        }
      ]
    },
    {
      "winner_id": 2053290,
      "loser_id": 383771,
      "winner_score": 2,
      "loser_score": 1,
      "round_text": "Winners Quarter-Final",
      "round": 2,
      "phase": "1",
      "wave": null,
      "dq": false,
      "cancel": false,
      "state": 3,
      "details": [
        {
          "game_id": 39029507,
          "order_num": 1,
          "winner_id": 2053290,
          "entrant1_score": null,
          "entrant2_score": null,
          "stage": null,
          "selections": [
            {
              "user_id": 383771,
              "selection_id": 58305123,
              "character_id": 1300,
              "character_name": "Lucina"
            },
            {
              "user_id": 2053290,
              "selection_id": 58305124,
              "character_id": 1846,
              "character_name": "Kazuya"
            }
          ]
        },
        {
          "game_id": 39029508,
          "order_num": 2,
          "winner_id": 383771,
          "entrant1_score": null,
          "entrant2_score": 0,
          "stage": null,
          "selections": [
            {
              "user_id": 383771,
              "selection_id": 58305125,
              "character_id": 1300,
              "character_name": "Lucina"
            },
            {
              "user_id": 2053290,
              "selection_id": 58305126,
              "character_id": 1846,
              "character_name": "Kazuya"
            }
          ]
        },
        {
          "game_id": 39029509,
          "order_num": 3,
          "winner_id": 2053290,
          "entrant1_score": 0,
          "entrant2_score": null,
          "stage": null,
          "selections": [
            {
              "user_id": 383771,
              "selection_id": 58305127,
              "character_id": 1300,
              "character_name": "Lucina"
            },
            {
              "user_id": 2053290,
              "selection_id": 58305128,
              "character_id": 1846,
              "character_name": "Kazuya"
            }
          ]
        }
      ]
    },
    {
      "winner_id": 1844513,
      "loser_id": 1453340,
      "winner_score": 2,
      "loser_score": 1,
      "round_text": "Winners Quarter-Final",
      "round": 2,
      "phase": "1",
      "wave": null,
      "dq": false,
      "cancel": false,
      "state": 3,
      "details": [
        {
          "game_id": 39029438,
          "order_num": 1,
          "winner_id": 1844513,
          "entrant1_score": 0,
          "entrant2_score": null,
          "stage": null,
          "selections": [
            {
              "user_id": 1453340,
              "selection_id": 58304985,
              "character_id": 1326,
              "character_name": "Roy"
            },
            {
              "user_id": 1844513,
              "selection_id": 58304986,
              "character_id": 1328,
              "character_name": "Samus"
            }
          ]
        },
        {
          "game_id": 39029439,
          "order_num": 2,
          "winner_id": 1453340,
          "entrant1_score": null,
          "entrant2_score": 0,
          "stage": null,
          "selections": [
            {
              "user_id": 1453340,
              "selection_id": 58304987,
              "character_id": 1326,
              "character_name": "Roy"
            },
            {
              "user_id": 1844513,
              "selection_id": 58304988,
              "character_id": 1328,
              "character_name": "Samus"
            }
          ]
        },
        {
          "game_id": 39029440,
          "order_num": 3,
          "winner_id": 1844513,
          "entrant1_score": 0,
          "entrant2_score": null,
          "stage": null,
          "selections": [
            {
              "user_id": 1453340,
              "selection_id": 58304989,
              "character_id": 1326,
              "character_name": "Roy"
            },
            {
              "user_id": 1844513,
              "selection_id": 58304990,
              "character_id": 1328,
              "character_name": "Samus"
            }
          ]
        }
      ]
    },
    {
      "winner_id": 1918910,
      "loser_id": 3414945,
      "winner_score": 2,
      "loser_score": 0,
      "round_text": "Winners Quarter-Final",
      "round": 2,
      "phase": "1",
      "wave": null,
      "dq": false,
      "cancel": false,
      "state": 3,
      "details": []
    },
    {
      "winner_id": 837458,
      "loser_id": 3414945,
      "winner_score": 2,
      "loser_score": 0,
      "round_text": "Losers Round 2",
      "round": -4,
      "phase": "1",
      "wave": null,
      "dq": false,
      "cancel": false,
      "state": 3,
      "details": []
    },
    {
      "winner_id": 1453340,
      "loser_id": 3280279,
      "winner_score": 2,
      "loser_score": 0,
      "round_text": "Losers Round 2",
      "round": -4,
      "phase": "1",
      "wave": null,
      "dq": false,
      "cancel": false,
      "state": 3,
      "details": []
    },
    {
      "winner_id": 383771,
      "loser_id": 1871109,
      "winner_score": 0,
      "loser_score": -1,
      "round_text": "Losers Round 2",
      "round": -4,
      "phase": "1",
      "wave": null,
      "dq": true,
      "cancel": false,
      "state": 3,
      "details": []
    },
    {
      "winner_id": 3031255,
      "loser_id": 2515351,
      "winner_score": 2,
      "loser_score": 0,
      "round_text": "Losers Round 2",
      "round": -4,
      "phase": "1",
      "wave": null,
      "dq": false,
      "cancel": false,
      "state": 3,
      "details": [
        {
          "game_id": 39029602,
          "order_num": 1,
          "winner_id": 3031255,
          "entrant1_score": null,
          "entrant2_score": null,
          "stage": null,
          "selections": [
            {
              "user_id": 2515351,
              "selection_id": 58305308,
              "character_id": 1280,
              "character_name": "Donkey Kong"
            },
            {
              "user_id": 3031255,
              "selection_id": 58305309,
              "character_id": 1336,
              "character_name": "Wii Fit Trainer"
            }
          ]
        },
        {
          "game_id": 39029603,
          "order_num": 2,
          "winner_id": 3031255,
          "entrant1_score": null,
          "entrant2_score": null,
          "stage": null,
          "selections": [
            {
              "user_id": 2515351,
              "selection_id": 58305310,
              "character_id": 1280,
              "character_name": "Donkey Kong"
            },
            {
              "user_id": 3031255,
              "selection_id": 58305311,
              "character_id": 1336,
              "character_name": "Wii Fit Trainer"
            }
          ]
        }
      ]
    },
    {
      "winner_id": 3280279,
      "loser_id": 3315261,
      "winner_score": 2,
      "loser_score": 0,
      "round_text": "Losers Round 1",
      "round": -3,
      "phase": "1",
      "wave": null,
      "dq": false,
      "cancel": false,
      "state": 3,
      "details": [
        {
          "game_id": 39029486,
          "order_num": 1,
          "winner_id": 3280279,
          "entrant1_score": null,
          "entrant2_score": null,
          "stage": null,
          "selections": [
            {
              "user_id": 3315261,
              "selection_id": 58305081,
              "character_id": 1316,
              "character_name": "Palutena"
            },
            {
              "user_id": 3280279,
              "selection_id": 58305082,
              "character_id": 1415,
              "character_name": "Mii Gunner"
            }
          ]
        },
        {
          "game_id": 39029487,
          "order_num": 2,
          "winner_id": 3280279,
          "entrant1_score": null,
          "entrant2_score": null,
          "stage": null,
          "selections": [
            {
              "user_id": 3315261,
              "selection_id": 58305083,
              "character_id": 1316,
              "character_name": "Palutena"
            },
            {
              "user_id": 3280279,
              "selection_id": 58305084,
              "character_id": 1279,
              "character_name": "Diddy Kong"
            }
          ]
        }
      ]
    },
    {
      "winner_id": 3031255,
      "loser_id": 2815631,
      "winner_score": 2,
      "loser_score": 0,
      "round_text": "Losers Round 1",
      "round": -3,
      "phase": "1",
      "wave": null,
      "dq": false,
      "cancel": false,
      "state": 3,
      "details": [
        {
          "game_id": 39029488,
          "order_num": 1,
          "winner_id": 3031255,
          "entrant1_score": null,
          "entrant2_score": null,
          "stage": null,
          "selections": [
            {
              "user_id": 2815631,
              "selection_id": 58305085,
              "character_id": 1336,
              "character_name": "Wii Fit Trainer"
            },
            {
              "user_id": 3031255,
              "selection_id": 58305086,
              "character_id": 1336,
              "character_name": "Wii Fit Trainer"
            }
          ]
        },
        {
          "game_id": 39029489,
          "order_num": 2,
          "winner_id": 3031255,
          "entrant1_score": null,
          "entrant2_score": null,
          "stage": null,
          "selections": [
            {
              "user_id": 2815631,
              "selection_id": 58305087,
              "character_id": 1336,
              "character_name": "Wii Fit Trainer"
            },
            {
              "user_id": 3031255,
              "selection_id": 58305088,
              "character_id": 1336,
              "character_name": "Wii Fit Trainer"
            }
          ]
        }
      ]
    },
    {
      "winner_id": 2515351,
      "loser_id": 837458,
      "winner_score": 2,
      "loser_score": 0,
      "round_text": "Winners Round 1",
      "round": 1,
      "phase": "1",
      "wave": null,
      "dq": false,
      "cancel": false,
      "state": 3,
      "details": []
    },
    {
      "winner_id": 383771,
      "loser_id": 3315261,
      "winner_score": 2,
      "loser_score": 0,
      "round_text": "Winners Round 1",
      "round": 1,
      "phase": "1",
      "wave": null,
      "dq": false,
      "cancel": false,
      "state": 3,
      "details": []
    },
    {
      "winner_id": 2053290,
      "loser_id": 3280279,
      "winner_score": 2,
      "loser_score": 1,
      "round_text": "Winners Round 1",
      "round": 1,
      "phase": "1",
      "wave": null,
      "dq": false,
      "cancel": false,
      "state": 3,
      "details": [
        {
          "game_id": 39029294,
          "order_num": 1,
          "winner_id": 2053290,
          "entrant1_score": null,
          "entrant2_score": 0,
          "stage": null,
          "selections": [
            {
              "user_id": 3280279,
              "selection_id": 58304700,
              "character_id": 1415,
              "character_name": "Mii Gunner"
            },
            {
              "user_id": 2053290,
              "selection_id": 58304701,
              "character_id": 1846,
              "character_name": "Kazuya"
            }
          ]
        },
        {
          "game_id": 39029295,
          "order_num": 2,
          "winner_id": 3280279,
          "entrant1_score": 0,
          "entrant2_score": null,
          "stage": null,
          "selections": [
            {
              "user_id": 3280279,
              "selection_id": 58304702,
              "character_id": 1415,
              "character_name": "Mii Gunner"
            },
            {
              "user_id": 2053290,
              "selection_id": 58304703,
              "character_id": 1846,
              "character_name": "Kazuya"
            }
          ]
        },
        {
          "game_id": 39029296,
          "order_num": 3,
          "winner_id": 2053290,
          "entrant1_score": null,
          "entrant2_score": 0,
          "stage": null,
          "selections": [
            {
              "user_id": 3280279,
              "selection_id": 58304704,
              "character_id": 1415,
              "character_name": "Mii Gunner"
            },
            {
              "user_id": 2053290,
              "selection_id": 58304705,
              "character_id": 1846,
              "character_name": "Kazuya"
            }
          ]
        }
      ]
    },
    {
      "winner_id": 1844513,
      "loser_id": 1871109,
      "winner_score": 0,
      "loser_score": -1,
      "round_text": "Winners Round 1",
      "round": 1,
      "phase": "1",
      "wave": null,
      "dq": true,
      "cancel": false,
      "state": 3,
      "details": []
    },
    {
      "winner_id": 3414945,
      "loser_id": 3031255,
      "winner_score": 2,
      "loser_score": 1,
      "round_text": "Winners Round 1",
      "round": 1,
      "phase": "1",
      "wave": null,
      "dq": false,
      "cancel": false,
      "state": 3,
      "details": [
        {
          "game_id": 39029301,
          "order_num": 1,
          "winner_id": 3031255,
          "entrant1_score": null,
          "entrant2_score": 0,
          "stage": null,
          "selections": [
            {
              "user_id": 3414945,
              "selection_id": 58304714,
              "character_id": 1286,
              "character_name": "Fox"
            }
          ]
        },
        {
          "game_id": 39029302,
          "order_num": 2,
          "winner_id": 3414945,
          "entrant1_score": 0,
          "entrant2_score": null,
          "stage": null,
          "selections": [
            {
              "user_id": 3414945,
              "selection_id": 58304715,
              "character_id": 1286,
              "character_name": "Fox"
            }
          ]
        },
        {
          "game_id": 39029303,
          "order_num": 3,
          "winner_id": 3414945,
          "entrant1_score": 0,
          "entrant2_score": null,
          "stage": null,
          "selections": [
            {
              "user_id": 3414945,
              "selection_id": 58304716,
              "character_id": 1286,
              "character_name": "Fox"
            }
          ]
        }
      ]
    },
    {
      "winner_id": 1918910,
      "loser_id": 2815631,
      "winner_score": 2,
      "loser_score": 0,
      "round_text": "Winners Round 1",
      "round": 1,
      "phase": "1",
      "wave": null,
      "dq": false,
      "cancel": false,
      "state": 3,
      "details": [
        {
          "game_id": 39029337,
          "order_num": 1,
          "winner_id": 1918910,
          "entrant1_score": null,
          "entrant2_score": 0,
          "stage": null,
          "selections": [
            {
              "user_id": 1918910,
              "selection_id": 58304783,
              "character_id": 1289,
              "character_name": "Greninja"
            },
            {
              "user_id": 2815631,
              "selection_id": 58304784,
              "character_id": 1336,
              "character_name": "Wii Fit Trainer"
            }
          ]
        },
        {
          "game_id": 39029338,
          "order_num": 2,
          "winner_id": 1918910,
          "entrant1_score": null,
          "entrant2_score": null,
          "stage": null,
          "selections": [
            {
              "user_id": 1918910,
              "selection_id": 58304785,
              "character_id": 1289,
              "character_name": "Greninja"
            },
            {
              "user_id": 2815631,
              "selection_id": 58304786,
              "character_id": 1336,
              "character_name": "Wii Fit Trainer"
            }
          ]
        }
      ]
    }
  ],
  "version": "1.0"
}