{
  "data": [
    {
      "winner_id": 2523228,
      "loser_id": 840764,
      "winner_score": 3,
      "loser_score": 2,
      "round_text": "Grand Final",
      "round": 6,
      "phase": "1",
      "wave": null,
      "dq": false,
      "cancel": false,
      "state": 3,
      "details": []
    },
    {
      "winner_id": 2523228,
      "loser_id": 1636770,
      "winner_score": 3,
      "loser_score": 2,
      "round_text": "Winners Final",
      "round": 5,
      "phase": "1",
      "wave": null,
      "dq": false,
      "cancel": false,
      "state": 3,
      "details": []
    },
    {
      "winner_id": 840764,
      "loser_id": 1636770,
      "winner_score": 3,
      "loser_score": 2,
      "round_text": "Losers Final",
      "round": -10,
      "phase": "1",
      "wave": null,
      "dq": false,
      "cancel": false,
      "state": 3,
      "details": []
    },
    {
      "winner_id": 840764,
      "loser_id": 1792751,
      "winner_score": 3,
      "loser_score": 0,
      "round_text": "Losers Semi-Final",
      "round": -9,
      "phase": "1",
      "wave": null,
      "dq": false,
      "cancel": false,
      "state": 3,
      "details": []
    },
    {
      "winner_id": 1636770,
      "loser_id": 840764,
      "winner_score": 3,
      "loser_score": 2,
      "round_text": "Winners Semi-Final",
      "round": 4,
      "phase": "1",
      "wave": null,
      "dq": false,
      "cancel": false,
      "state": 3,
      "details": []
    },
    {
      "winner_id": 2523228,
      "loser_id": 1792751,
      "winner_score": 3,
      "loser_score": 2,
      "round_text": "Winners Semi-Final",
      "round": 4,
      "phase": "1",
      "wave": null,
      "dq": false,
      "cancel": false,
      "state": 3,
      "details": []
    },
    {
      "winner_id": 1792751,
      "loser_id": 95379,
      "winner_score": 3,
      "loser_score": 2,
      "round_text": "Losers Quarter-Final",
      "round": -8,
      "phase": "1",
      "wave": null,
      "dq": false,
      "cancel": false,
      "state": 3,
      "details": []
    },
    {
      "winner_id": 840764,
      "loser_id": 3086480,
      "winner_score": 3,
      "loser_score": 2,
      "round_text": "Losers Quarter-Final",
      "round": -8,
      "phase": "1",
      "wave": null,
      "dq": false,
      "cancel": false,
      "state": 3,
      "details": []
    },
    {
      "winner_id": 95379,
      "loser_id": 927362,
      "winner_score": 3,
      "loser_score": 0,
      "round_text": "Losers Round 4",
      "round": -7,
      "phase": "1",
      "wave": null,
      "dq": false,
      "cancel": false,
      "state": 3,
      "details": []
    },
    {
      "winner_id": 3086480,
      "loser_id": 1804317,
      "winner_score": 3,
      "loser_score": 2,
      "round_text": "Losers Round 4",
      "round": -7,
      "phase": "1",
      "wave": null,
      "dq": false,
      "cancel": false,
      "state": 3,
      "details": []
    },
    {
      "winner_id": 1636770,
      "loser_id": 927362,
      "winner_score": 2,
      "loser_score": 1,
      "round_text": "Winners Quarter-Final",
      "round": 3,
      "phase": "1",
      "wave": null,
      "dq": false,
      "cancel": false,
      "state": 3,
      "details": []
    },
    {
      "winner_id": 840764,
      "loser_id": 2718972,
      "winner_score": 2,
      "loser_score": 0,
      "round_text": "Winners Quarter-Final",
      "round": 3,
      "phase": "1",
      "wave": null,
      "dq": false,
      "cancel": false,
      "state": 3,
      "details": []
    },
    {
      "winner_id": 1792751,
      "loser_id": 1804317,
      "winner_score": 2,
      "loser_score": 1,
      "round_text": "Winners Quarter-Final",
      "round": 3,
      "phase": "1",
      "wave": null,
      "dq": false,
      "cancel": false,
      "state": 3,
      "details": []
    },
    {
      "winner_id": 2523228,
      "loser_id": 3086480,
      "winner_score": 2,
      "loser_score": 0,
      "round_text": "Winners Quarter-Final",
      "round": 3,
      "phase": "1",
      "wave": null,
      "dq": false,
      "cancel": false,
      "state": 3,
      "details": []
    },
    {
      "winner_id": 95379,
      "loser_id": 2718972,
      "winner_score": 3,
      "loser_score": 2,
      "round_text": "Losers Round 3",
      "round": -6,
      "phase": "1",
      "wave": null,
      "dq": false,
      "cancel": false,
      "state": 3,
      "details": []
    },
    {
      "winner_id": 927362,
      "loser_id": 3153137,
      "winner_score": 3,
      "loser_score": 1,
      "round_text": "Losers Round 3",
      "round": -6,
      "phase": "1",
      "wave": null,
      "dq": false,
      "cancel": false,
      "state": 3,
      "details": []
    },
    {
      "winner_id": 3086480,
      "loser_id": 167279,
      "winner_score": 3,
      "loser_score": 1,
      "round_text": "Losers Round 3",
      "round": -6,
      "phase": "1",
      "wave": null,
      "dq": false,
      "cancel": false,
      "state": 3,
      "details": []
    },
    {
      "winner_id": 1804317,
      "loser_id": 837605,
      "winner_score": 3,
      "loser_score": 2,
      "round_text": "Losers Round 3",
      "round": -6,
      "phase": "1",
      "wave": null,
      "dq": false,
      "cancel": false,
      "state": 3,
      "details": []
    },
    {
      "winner_id": 837605,
      "loser_id": 2429854,
      "winner_score": 2,
      "loser_score": 0,
      "round_text": "Losers Round 2",
      "round": -5,
      "phase": "1",
      "wave": null,
      "dq": false,
      "cancel": false,
      "state": 3,
      "details": []
    },
    {
      "winner_id": 95379,
      "loser_id": 926294,
      "winner_score": 2,
      "loser_score": 0,
      "round_text": "Losers Round 2",
      "round": -5,
      "phase": "1",
      "wave": null,
      "dq": false,
      "cancel": false,
      "state": 3,
      "details": []
    },
    {
      "winner_id": 3153137,
      "loser_id": 2409926,
      "winner_score": 2,
      "loser_score": 1,
      "round_text": "Losers Round 2",
      "round": -5,
      "phase": "1",
      "wave": null,
      "dq": false,
      "cancel": false,
      "state": 3,
      "details": []
    },
    {
      "winner_id": 167279,
      "loser_id": 1788877,
      "winner_score": 2,
      "loser_score": 0,
      "round_text": "Losers Round 2",
      "round": -5,
      "phase": "1",
      "wave": null,
      "dq": false,
      "cancel": false,
      "state": 3,
      "details": []
    },
    {
      "winner_id": 1636770,
      "loser_id": 2429854,
      "winner_score": 2,
      "loser_score": 0,
      "round_text": "Winners Round 2",
      "round": 2,
      "phase": "1",
      "wave": null,
      "dq": false,
      "cancel": false,
      "state": 3,
      "details": []
    },
    {
      "winner_id": 927362,
      "loser_id": 837605,
      "winner_score": 2,
      "loser_score": 0,
      "round_text": "Winners Round 2",
      "round": 2,
      "phase": "1",
      "wave": null,
      "dq": false,
      "cancel": false,
      "state": 3,
      "details": []
    },
    {
      "winner_id": 840764,
      "loser_id": 1788877,
      "winner_score": 2,
      "loser_score": 0,
      "round_text": "Winners Round 2",
      "round": 2,
      "phase": "1",
      "wave": null,
      "dq": false,
      "cancel": false,
      "state": 3,
      "details": []
    },
    {
      "winner_id": 2718972,
      "loser_id": 2939638,
      "winner_score": 2,
      "loser_score": 0,
      "round_text": "Winners Round 2",
      "round": 2,
      "phase": "1",
      "wave": null,
      "dq": false,
      "cancel": false,
      "state": 3,
      "details": []
    },
    {
      "winner_id": 1792751,
      "loser_id": 2409926,
      "winner_score": 2,
      "loser_score": 1,
      "round_text": "Winners Round 2",
      "round": 2,
      "phase": "1",
      "wave": null,
      "dq": false,
      "cancel": false,
      "state": 3,
      "details": []
    },
    {
      "winner_id": 1804317,
      "loser_id": 3153137,
      "winner_score": 2,
      "loser_score": 0,
      "round_text": "Winners Round 2",
      "round": 2,
      "phase": "1",
      "wave": null,
      "dq": false,
      "cancel": false,
      "state": 3,
      "details": []
    },
    {
      "winner_id": 3086480,
      "loser_id": 926294,
      "winner_score": 2,
      "loser_score": 1,
      "round_text": "Winners Round 2",
      "round": 2,
      "phase": "1",
      "wave": null,
      "dq": false,
      "cancel": false,
      "state": 3,
      "details": []
    },
    {
      "winner_id": 2523228,
      "loser_id": 95379,
      "winner_score": 2,
      "loser_score": 0,
      "round_text": "Winners Round 2",
      "round": 2,
      "phase": "1",
      "wave": null,
      "dq": false,
      "cancel": false,
      "state": 3,
      "details": []
    },
    {
      "winner_id": 95379,
      "loser_id": 2167937,
      "winner_score": 2,
      "loser_score": 0,
      "round_text": "Losers Round 1",
      "round": -4,
      "phase": "1",
      "wave": null,
      "dq": false,
      "cancel": false,
      "state": 3,
      "details": [
        {
          "game_id": 39029286,
          "order_num": 1,
          "winner_id": 95379,
          "entrant1_score": null,
          "entrant2_score": null,
          "stage": "Final Destination",
          "selections": [
            {
              "user_id": 2167937,
              "selection_id": 58304684,
              "character_id": 1275,
              "character_name": "Cloud"
            },
            {
              "user_id": 95379,
              "selection_id": 58304685,
              "character_id": 1331,
              "character_name": "Snake"
            }
          ]
        },
        {
          "game_id": 39029287,
          "order_num": 2,
          "winner_id": 95379,
          "entrant1_score": null,
          "entrant2_score": null,
          "stage": "Town and City",
          "selections": [
            {
              "user_id": 2167937,
              "selection_id": 58304686,
              "character_id": 1275,
              "character_name": "Cloud"
            },
            {
              "user_id": 95379,
              "selection_id": 58304687,
              "character_id": 1331,
              "character_name": "Snake"
            }
          ]
        }
      ]
    },
    {
      "winner_id": 167279,
      "loser_id": 2939638,
      "winner_score": 2,
      "loser_score": 0,
      "round_text": "Losers Round 1",
      "round": -4,
      "phase": "1",
      "wave": null,
      "dq": false,
      "cancel": false,
      "state": 3,
      "details": []
    },
    {
      "winner_id": 837605,
      "loser_id": 3384591,
      "winner_score": 2,
      "loser_score": 0,
      "round_text": "Losers Round 1",
      "round": -4,
      "phase": "1",
      "wave": null,
      "dq": false,
      "cancel": false,
      "state": 3,
      "details": []
    },
    {
      "winner_id": 2429854,
      "loser_id": 2167937,
      "winner_score": 2,
      "loser_score": 0,
      "round_text": "Winners Round 1",
      "round": 1,
      "phase": "1",
      "wave": null,
      "dq": false,
      "cancel": false,
      "state": 3,
      "details": [
        {
          "game_id": 39029092,
          "order_num": 1,
          "winner_id": 2429854,
          "entrant1_score": null,
          "entrant2_score": null,
          "stage": "Hollow Bastion",
          "selections": [
            {
              "user_id": 2167937,
              "selection_id": 58304296,
              "character_id": 1275,
              "character_name": "Cloud"
            },
            {
              "user_id": 2429854,
              "selection_id": 58304297,
              "character_id": 1453,
              "character_name": "Joker"
            }
          ]
        },
        {
          "game_id": 39029093,
          "order_num": 2,
          "winner_id": 2429854,
          "entrant1_score": null,
          "entrant2_score": null,
          "stage": "Town and City",
          "selections": [
            {
              "user_id": 2167937,
              "selection_id": 58304298,
              "character_id": 1275,
              "character_name": "Cloud"
            },
            {
              "user_id": 2429854,
              "selection_id": 58304299,
              "character_id": 1453,
              "character_name": "Joker"
            }
          ]
        }
      ]
    },
    {
      "winner_id": 2409926,
      "loser_id": 167279,
      "winner_score": 2,
      "loser_score": 0,
      "round_text": "Winners Round 1",
      "round": 1,
      "phase": "1",
      "wave": null,
      "dq": false,
      "cancel": false,
      "state": 3,
      "details": []
    },
    {
      "winner_id": 3086480,
      "loser_id": 3384591,
      "winner_score": 2,
      "loser_score": 1,
      "round_text": "Winners Round 1",
      "round": 1,
      "phase": "1",
      "wave": null,
      "dq": false,
      "cancel": false,
      "state": 3,
      "details": []
    }
  ],
  "version": "1.0"
}