{
  "data": [
    {
      "placement": 1,
      "user_id": 1912360
    },
    {
      "placement": 2,
      "user_id": 1309481
    },
    {
      "placement": 3,
      "user_id": 1638015
    },
    {
      "placement": 4,
      "user_id": 1846904
    },
    {
      "placement": 5,
      "user_id": 2377204
    },
    {
      "placement": 5,
      "user_id": 1731916
    },
    {
      "placement": 7,
      "user_id": 926294
    },
    {
      "placement": 7,
      "user_id": 841065
    },
    {
      "placement": 9,
      "user_id": 2378414
    },
    {
      "placement": 9,
      "user_id": 926998
    },
    {
      "placement": 9,
      "user_id": 2971239
    },
    {
      "placement": 9,
      "user_id": 994990
    },
    {
      "placement": 13,
      "user_id": 2531222
    },
    {
      "placement": 13,
      "user_id": 1669715
    },
    {
      "placement": 13,
      "user_id": 1963941
    },
    {
      "placement": 13,
      "user_id": 2432471
    },
    {
      "placement": 17,
      "user_id": 866419
    },
    {
      "placement": 17,
      "user_id": 3223132
    },
    {
      "placement": 17,
      "user_id": 1890365
    },
    {
      "placement": 17,
      "user_id": 2633132
    },
    {
      "placement": 17,
      "user_id": 1469278
    },
    {
      "placement": 17,
      "user_id": 2449294
    },
    {
      "placement": 17,
      "user_id": 1944921
    },
    {
      "placement": 17,
      "user_id": 2158467
    },
    {
      "placement": 25,
      "user_id": 2975815
    },
    {
      "placement": 25,
      "user_id": 1304178
    },
    {
      "placement": 25,
      "user_id": 926291
    },
    {
      "placement": 25,
      "user_id": 2954842
    },
    {
      "placement": 25,
      "user_id": 3159865
    },
    {
      "placement": 25,
      "user_id": 1033803
    },
    {
      "placement": 25,
      "user_id": 2062615
    },
    {
      "placement": 25,
      "user_id": 2132927
    },
    {
      "placement": 33,
      "user_id": 913409
    },
    {
      "placement": 33,
      "user_id": 2633155
    },
    {
      "placement": 33,
      "user_id": 2153833
    },
    {
      "placement": 33,
      "user_id": 2544776
    },
    {
      "placement": 33,
      "user_id": 2400645
    },
    {
      "placement": 33,
      "user_id": 1378787
    },
    {
      "placement": 33,
      "user_id": 1943733
    },
    {
      "placement": 33,
      "user_id": 1931928
    },
    {
      "placement": 33,
      "user_id": 1454631
    },
    {
      "placement": 33,
      "user_id": 1805102
    },
    {
      "placement": 33,
      "user_id": 2177907
    },
    {
      "placement": 33,
      "user_id": 1984900
    },
    {
      "placement": 33,
      "user_id": 1692207
    },
    {
      "placement": 33,
      "user_id": 2311673
    },
    {
      "placement": 33,
      "user_id": 1036269
    },
    {
      "placement": 33,
      "user_id": 1876240
    },
    {
      "placement": 49,
      "user_id": 2110626
    },
    {
      "placement": 49,
      "user_id": 921440
    },
    {
      "placement": 49,
      "user_id": 2064336
    },
    {
      "placement": 49,
      "user_id": 3031108
    },
    {
      "placement": 49,
      "user_id": 1719453
    },
    {
      "placement": 49,
      "user_id": 2372545
    },
    {
      "placement": 49,
      "user_id": 2632670
    },
    {
      "placement": 49,
      "user_id": 2027460
    },
    {
      "placement": 49,
      "user_id": 1444099
    },
    {
      "placement": 49,
      "user_id": 3269166
    },
    {
      "placement": 49,
      "user_id": 2633073
    },
    {
      "placement": 49,
      "user_id": 1896967
    },
    {
      "placement": 49,
      "user_id": 2062690
    },
    {
      "placement": 49,
      "user_id": 2106141
    },
    {
      "placement": 49,
      "user_id": 839849
    },
    {
      "placement": 49,
      "user_id": 2017004
    },
    {
      "placement": 65,
      "user_id": 2162969
    },
    {
      "placement": 65,
      "user_id": 2723453
    },
    {
      "placement": 65,
      "user_id": 2526245
    },
    {
      "placement": 65,
      "user_id": 2849143
    },
    {
      "placement": 65,
      "user_id": 1453924
    },
    {
      "placement": 65,
      "user_id": 2469617
    },
    {
      "placement": 65,
      "user_id": 2031853
    },
    {
      "placement": 65,
      "user_id": 2368253
    },
    {
      "placement": 65,
      "user_id": 2031148
    },
    {
      "placement": 65,
      "user_id": 2607718
    },
    {
      "placement": 65,
      "user_id": 837326
    },
    {
      "placement": 65,
      "user_id": 1517331
    },
    {
      "placement": 65,
      "user_id": 2414495
    },
    {
      "placement": 65,
      "user_id": 2616902
    },
    {
      "placement": 65,
      "user_id": 2427455
    },
    {
      "placement": 65,
      "user_id": 2233732
    },
    {
      "placement": 65,
      "user_id": 1896320
    },
    {
      "placement": 65,
      "user_id": 2381379
    },
    {
      "placement": 65,
      "user_id": 3226423
    },
    {
      "placement": 65,
      "user_id": 3346876
    },
    {
      "placement": 65,
      "user_id": 2565837
    },
    {
      "placement": 65,
      "user_id": 3368705
    },
    {
      "placement": 65,
      "user_id": 2371517
    },
    {
      "placement": 65,
      "user_id": 2805721
    },
    {
      "placement": 65,
      "user_id": 2633169
    },
    {
      "placement": 65,
      "user_id": 1853608
    },
    {
      "placement": 65,
      "user_id": 2091174
    },
    {
      "placement": 65,
      "user_id": 3357152
    },
    {
      "placement": 65,
      "user_id": 1035525
    },
    {
      "placement": 65,
      "user_id": 3357525
    },
    {
      "placement": 65,
      "user_id": 2165682
    },
    {
      "placement": 65,
      "user_id": 2830099
    },
    {
      "placement": 97,
      "user_id": 3039644
    },
    {
      "placement": 97,
      "user_id": 2930232
    },
    {
      "placement": 97,
      "user_id": 3368722
    },
    {
      "placement": 97,
      "user_id": 2935966
    },
    {
      "placement": 97,
      "user_id": 2723207
    },
    {
      "placement": 97,
      "user_id": 3345423
    },
    {
      "placement": 97,
      "user_id": 3320308
    },
    {
      "placement": 97,
      "user_id": 1783283
    },
    {
      "placement": 97,
      "user_id": 3234159
    },
    {
      "placement": 97,
      "user_id": 995092
    },
    {
      "placement": 97,
      "user_id": 2484073
    },
    {
      "placement": 97,
      "user_id": 2818152
    },
    {
      "placement": 97,
      "user_id": 3132376
    },
    {
      "placement": 97,
      "user_id": 922452
    },
    {
      "placement": 97,
      "user_id": 2616886
    }
  ],
  "version": "1.0"
}