{
  "data": [
    {
      "winner_id": 134839,
      "loser_id": 346254,
      "winner_score": 2,
      "loser_score": 0,
      "round_text": "Grand Final",
      "round": 7,
      "phase": "1",
      "wave": null,
      "dq": false,
      "cancel": false,
      "state": 3,
      "details": [
        {
          "game_id": 38478722,
          "order_num": 1,
          "winner_id": 134839,
          "entrant1_score": 0,
          "entrant2_score": null,
          "stage": "Pokémon Stadium 2",
          "selections": [
            {
              "user_id": 134839,
              "selection_id": 57499039,
              "character_id": 1795,
              "character_name": "Pyra & Mythra"
            },
            {
              "user_id": 346254,
              "selection_id": 57499040,
              "character_id": 1313,
              "character_name": "Ness"
            }
          ]
        },
        {
          "game_id": 38478723,
          "order_num": 2,
          "winner_id": 134839,
          "entrant1_score": 0,
          "entrant2_score": null,
          "stage": "Pokémon Stadium 2",
          "selections": [
            {
              "user_id": 134839,
              "selection_id": 57499041,
              "character_id": 1795,
              "character_name": "Pyra & Mythra"
            },
            {
              "user_id": 346254,
              "selection_id": 57499042,
              "character_id": 1313,
              "character_name": "Ness"
            }
          ]
        }
      ]
    },
    {
      "winner_id": 134839,
      "loser_id": 346254,
      "winner_score": 2,
      "loser_score": 0,
      "round_text": "Grand Final Reset",
      "round": 7,
      "phase": "1",
      "wave": null,
      "dq": false,
      "cancel": false,
      "state": 3,
      "details": [
        {
          "game_id": 38478725,
          "order_num": 1,
          "winner_id": 134839,
          "entrant1_score": null,
          "entrant2_score": 0,
          "stage": "Pokémon Stadium 2",
          "selections": [
            {
              "user_id": 134839,
              "selection_id": 57499045,
              "character_id": 1795,
              "character_name": "Pyra & Mythra"
            },
            {
              "user_id": 346254,
              "selection_id": 57499046,
              "character_id": 1313,
              "character_name": "Ness"
            }
          ]
        },
        {
          "game_id": 38478726,
          "order_num": 2,
          "winner_id": 134839,
          "entrant1_score": null,
          "entrant2_score": 0,
          "stage": "Hollow Bastion",
          "selections": [
            {
              "user_id": 134839,
              "selection_id": 57499047,
              "character_id": 1795,
              "character_name": "Pyra & Mythra"
            },
            {
              "user_id": 346254,
              "selection_id": 57499048,
              "character_id": 1313,
              "character_name": "Ness"
            }
          ]
        }
      ]
    },
    {
      "winner_id": 346254,
      "loser_id": 134839,
      "winner_score": 2,
      "loser_score": 1,
      "round_text": "Winners Final",
      "round": 6,
      "phase": "1",
      "wave": null,
      "dq": false,
      "cancel": false,
      "state": 3,
      "details": [
        {
          "game_id": 38478614,
          "order_num": 1,
          "winner_id": 134839,
          "entrant1_score": null,
          "entrant2_score": 0,
          "stage": "Pokémon Stadium 2",
          "selections": [
            {
              "user_id": 134839,
              "selection_id": 57498829,
              "character_id": 1795,
              "character_name": "Pyra & Mythra"
            },
            {
              "user_id": 346254,
              "selection_id": 57498830,
              "character_id": 1313,
              "character_name": "Ness"
            }
          ]
        },
        {
          "game_id": 38478633,
          "order_num": 2,
          "winner_id": 346254,
          "entrant1_score": 0,
          "entrant2_score": null,
          "stage": "Pokémon Stadium 2",
          "selections": [
            {
              "user_id": 134839,
              "selection_id": 57498867,
              "character_id": 1795,
              "character_name": "Pyra & Mythra"
            },
            {
              "user_id": 346254,
              "selection_id": 57498868,
              "character_id": 1313,
              "character_name": "Ness"
            }
          ]
        },
        {
          "game_id": 38478634,
          "order_num": 3,
          "winner_id": 346254,
          "entrant1_score": 0,
          "entrant2_score": null,
          "stage": "Hollow Bastion",
          "selections": [
            {
              "user_id": 134839,
              "selection_id": 57498869,
              "character_id": 1795,
              "character_name": "Pyra & Mythra"
            },
            {
              "user_id": 346254,
              "selection_id": 57498870,
              "character_id": 1313,
              "character_name": "Ness"
            }
          ]
        }
      ]
    },
    {
      "winner_id": 134839,
      "loser_id": 1157521,
      "winner_score": 2,
      "loser_score": 0,
      "round_text": "Losers Final",
      "round": -12,
      "phase": "1",
      "wave": null,
      "dq": false,
      "cancel": false,
      "state": 3,
      "details": [
        {
          "game_id": 38478665,
          "order_num": 1,
          "winner_id": 134839,
          "entrant1_score": null,
          "entrant2_score": 0,
          "stage": "Small Battlefield",
          "selections": [
            {
              "user_id": 134839,
              "selection_id": 57498931,
              "character_id": 1795,
              "character_name": "Pyra & Mythra"
            },
            {
              "user_id": 1157521,
              "selection_id": 57498932,
              "character_id": 1897,
              "character_name": "Sora"
            }
          ]
        },
        {
          "game_id": 38478681,
          "order_num": 2,
          "winner_id": 134839,
          "entrant1_score": null,
          "entrant2_score": 0,
          "stage": "Pokémon Stadium 2",
          "selections": [
            {
              "user_id": 134839,
              "selection_id": 57498963,
              "character_id": 1795,
              "character_name": "Pyra & Mythra"
            },
            {
              "user_id": 1157521,
              "selection_id": 57498964,
              "character_id": 1897,
              "character_name": "Sora"
            }
          ]
        }
      ]
    },
    {
      "winner_id": 1157521,
      "loser_id": 2151157,
      "winner_score": 2,
      "loser_score": 0,
      "round_text": "Losers Semi-Final",
      "round": -11,
      "phase": "1",
      "wave": null,
      "dq": false,
      "cancel": false,
      "state": 3,
      "details": [
        {
          "game_id": 38478648,
          "order_num": 1,
          "winner_id": 1157521,
          "entrant1_score": 0,
          "entrant2_score": null,
          "stage": "Small Battlefield",
          "selections": [
            {
              "user_id": 1157521,
              "selection_id": 57498897,
              "character_id": 1526,
              "character_name": "Hero"
            },
            {
              "user_id": 2151157,
              "selection_id": 57498898,
              "character_id": 1326,
              "character_name": "Roy"
            }
          ]
        },
        {
          "game_id": 38478649,
          "order_num": 2,
          "winner_id": 1157521,
          "entrant1_score": 0,
          "entrant2_score": null,
          "stage": "Small Battlefield",
          "selections": [
            {
              "user_id": 1157521,
              "selection_id": 57498899,
              "character_id": 1526,
              "character_name": "Hero"
            },
            {
              "user_id": 2151157,
              "selection_id": 57498900,
              "character_id": 1326,
              "character_name": "Roy"
            }
          ]
        }
      ]
    },
    {
      "winner_id": 134839,
      "loser_id": 2151157,
      "winner_score": 2,
      "loser_score": 0,
      "round_text": "Winners Semi-Final",
      "round": 5,
      "phase": "1",
      "wave": null,
      "dq": false,
      "cancel": false,
      "state": 3,
      "details": [
        {
          "game_id": 38478418,
          "order_num": 1,
          "winner_id": 134839,
          "entrant1_score": null,
          "entrant2_score": 0,
          "stage": "Pokémon Stadium 2",
          "selections": [
            {
              "user_id": 134839,
              "selection_id": 57498437,
              "character_id": 1314,
              "character_name": "Olimar"
            },
            {
              "user_id": 2151157,
              "selection_id": 57498438,
              "character_id": 1331,
              "character_name": "Snake"
            }
          ]
        },
        {
          "game_id": 38478420,
          "order_num": 2,
          "winner_id": 134839,
          "entrant1_score": null,
          "entrant2_score": 0,
          "stage": "Pokémon Stadium 2",
          "selections": [
            {
              "user_id": 134839,
              "selection_id": 57498441,
              "character_id": 1314,
              "character_name": "Olimar"
            },
            {
              "user_id": 2151157,
              "selection_id": 57498442,
              "character_id": 1331,
              "character_name": "Snake"
            }
          ]
        }
      ]
    },
    {
      "winner_id": 346254,
      "loser_id": 2028400,
      "winner_score": 2,
      "loser_score": 1,
      "round_text": "Winners Semi-Final",
      "round": 5,
      "phase": "1",
      "wave": null,
      "dq": false,
      "cancel": false,
      "state": 3,
      "details": [
        {
          "game_id": 38478407,
          "order_num": 1,
          "winner_id": 346254,
          "entrant1_score": null,
          "entrant2_score": 0,
          "stage": null,
          "selections": [
            {
              "user_id": 2028400,
              "selection_id": 57498415,
              "character_id": 1323,
              "character_name": "R.O.B."
            },
            {
              "user_id": 346254,
              "selection_id": 57498416,
              "character_id": 1313,
              "character_name": "Ness"
            }
          ]
        },
        {
          "game_id": 38478408,
          "order_num": 2,
          "winner_id": 2028400,
          "entrant1_score": 0,
          "entrant2_score": null,
          "stage": null,
          "selections": [
            {
              "user_id": 2028400,
              "selection_id": 57498417,
              "character_id": 1323,
              "character_name": "R.O.B."
            },
            {
              "user_id": 346254,
              "selection_id": 57498418,
              "character_id": 1313,
              "character_name": "Ness"
            }
          ]
        },
        {
          "game_id": 38478437,
          "order_num": 3,
          "winner_id": 346254,
          "entrant1_score": null,
          "entrant2_score": 0,
          "stage": null,
          "selections": [
            {
              "user_id": 2028400,
              "selection_id": 57498473,
              "character_id": 1323,
              "character_name": "R.O.B."
            },
            {
              "user_id": 346254,
              "selection_id": 57498474,
              "character_id": 1313,
              "character_name": "Ness"
            }
          ]
        }
      ]
    },
    {
      "winner_id": 2151157,
      "loser_id": 1629776,
      "winner_score": 2,
      "loser_score": 1,
      "round_text": "Losers Quarter-Final",
      "round": -10,
      "phase": "1",
      "wave": null,
      "dq": false,
      "cancel": false,
      "state": 3,
      "details": [
        {
          "game_id": 38478565,
          "order_num": 1,
          "winner_id": 2151157,
          "entrant1_score": null,
          "entrant2_score": 0,
          "stage": null,
          "selections": [
            {
              "user_id": 1629776,
              "selection_id": 57498731,
              "character_id": 1289,
              "character_name": "Greninja"
            },
            {
              "user_id": 2151157,
              "selection_id": 57498732,
              "character_id": 1339,
              "character_name": "Young Link"
            }
          ]
        },
        {
          "game_id": 38478566,
          "order_num": 2,
          "winner_id": 1629776,
          "entrant1_score": 0,
          "entrant2_score": null,
          "stage": null,
          "selections": [
            {
              "user_id": 1629776,
              "selection_id": 57498733,
              "character_id": 1289,
              "character_name": "Greninja"
            },
            {
              "user_id": 2151157,
              "selection_id": 57498734,
              "character_id": 1339,
              "character_name": "Young Link"
            }
          ]
        },
        {
          "game_id": 38478635,
          "order_num": 3,
          "winner_id": 2151157,
          "entrant1_score": null,
          "entrant2_score": 0,
          "stage": null,
          "selections": [
            {
              "user_id": 1629776,
              "selection_id": 57498871,
              "character_id": 1289,
              "character_name": "Greninja"
            },
            {
              "user_id": 2151157,
              "selection_id": 57498872,
              "character_id": 1339,
              "character_name": "Young Link"
            }
          ]
        }
      ]
    },
    {
      "winner_id": 1157521,
      "loser_id": 2028400,
      "winner_score": 2,
      "loser_score": 1,
      "round_text": "Losers Quarter-Final",
      "round": -10,
      "phase": "1",
      "wave": null,
      "dq": false,
      "cancel": false,
      "state": 3,
      "details": []
    },
    {
      "winner_id": 1629776,
      "loser_id": 1846904,
      "winner_score": 2,
      "loser_score": 0,
      "round_text": "Losers Round 6",
      "round": -9,
      "phase": "1",
      "wave": null,
      "dq": false,
      "cancel": false,
      "state": 3,
      "details": [
        {
          "game_id": 38478472,
          "order_num": 1,
          "winner_id": 1629776,
          "entrant1_score": null,
          "entrant2_score": 0,
          "stage": "Small Battlefield",
          "selections": [
            {
              "user_id": 1629776,
              "selection_id": 57498543,
              "character_id": 1289,
              "character_name": "Greninja"
            },
            {
              "user_id": 1846904,
              "selection_id": 57498544,
              "character_id": 1313,
              "character_name": "Ness"
            }
          ]
        },
        {
          "game_id": 38478513,
          "order_num": 2,
          "winner_id": 1629776,
          "entrant1_score": null,
          "entrant2_score": 0,
          "stage": "Small Battlefield",
          "selections": [
            {
              "user_id": 1629776,
              "selection_id": 57498627,
              "character_id": 1289,
              "character_name": "Greninja"
            },
            {
              "user_id": 1846904,
              "selection_id": 57498628,
              "character_id": 1313,
              "character_name": "Ness"
            }
          ]
        }
      ]
    },
    {
      "winner_id": 1157521,
      "loser_id": 1520970,
      "winner_score": 2,
      "loser_score": 0,
      "round_text": "Losers Round 6",
      "round": -9,
      "phase": "1",
      "wave": null,
      "dq": false,
      "cancel": false,
      "state": 3,
      "details": [
        {
          "game_id": 38478559,
          "order_num": 1,
          "winner_id": 1157521,
          "entrant1_score": null,
          "entrant2_score": 0,
          "stage": "Final Destination",
          "selections": [
            {
              "user_id": 1157521,
              "selection_id": 57498719,
              "character_id": 1897,
              "character_name": "Sora"
            },
            {
              "user_id": 1520970,
              "selection_id": 57498720,
              "character_id": 1323,
              "character_name": "R.O.B."
            }
          ]
        },
        {
          "game_id": 38478560,
          "order_num": 2,
          "winner_id": 1157521,
          "entrant1_score": null,
          "entrant2_score": 0,
          "stage": "Battlefield",
          "selections": [
            {
              "user_id": 1157521,
              "selection_id": 57498721,
              "character_id": 1897,
              "character_name": "Sora"
            },
            {
              "user_id": 1520970,
              "selection_id": 57498722,
              "character_id": 1323,
              "character_name": "R.O.B."
            }
          ]
        }
      ]
    },
    {
      "winner_id": 134839,
      "loser_id": 1157521,
      "winner_score": 2,
      "loser_score": 1,
      "round_text": "Winners Quarter-Final",
      "round": 4,
      "phase": "1",
      "wave": null,
      "dq": false,
      "cancel": false,
      "state": 3,
      "details": [
        {
          "game_id": 38478345,
          "order_num": 1,
          "winner_id": 134839,
          "entrant1_score": null,
          "entrant2_score": 0,
          "stage": "Small Battlefield",
          "selections": [
            {
              "user_id": 134839,
              "selection_id": 57498299,
              "character_id": 1795,
              "character_name": "Pyra & Mythra"
            },
            {
              "user_id": 1157521,
              "selection_id": 57498300,
              "character_id": 1526,
              "character_name": "Hero"
            }
          ]
        },
        {
          "game_id": 38478346,
          "order_num": 2,
          "winner_id": 1157521,
          "entrant1_score": 0,
          "entrant2_score": null,
          "stage": "Pokémon Stadium 2",
          "selections": [
            {
              "user_id": 134839,
              "selection_id": 57498301,
              "character_id": 1795,
              "character_name": "Pyra & Mythra"
            },
            {
              "user_id": 1157521,
              "selection_id": 57498302,
              "character_id": 1526,
              "character_name": "Hero"
            }
          ]
        },
        {
          "game_id": 38478347,
          "order_num": 3,
          "winner_id": 134839,
          "entrant1_score": null,
          "entrant2_score": 0,
          "stage": "Small Battlefield",
          "selections": [
            {
              "user_id": 134839,
              "selection_id": 57498303,
              "character_id": 1795,
              "character_name": "Pyra & Mythra"
            },
            {
              "user_id": 1157521,
              "selection_id": 57498304,
              "character_id": 1526,
              "character_name": "Hero"
            }
          ]
        }
      ]
    },
    {
      "winner_id": 2151157,
      "loser_id": 2322500,
      "winner_score": 2,
      "loser_score": 0,
      "round_text": "Winners Quarter-Final",
      "round": 4,
      "phase": "1",
      "wave": null,
      "dq": false,
      "cancel": false,
      "state": 3,
      "details": [
        {
          "game_id": 38478404,
          "order_num": 1,
          "winner_id": 2151157,
          "entrant1_score": null,
          "entrant2_score": 0,
          "stage": null,
          "selections": [
            {
              "user_id": 2322500,
              "selection_id": 57498411,
              "character_id": 1331,
              "character_name": "Snake"
            },
            {
              "user_id": 2151157,
              "selection_id": 57498412,
              "character_id": 1339,
              "character_name": "Young Link"
            }
          ]
        },
        {
          "game_id": 38478405,
          "order_num": 2,
          "winner_id": 2151157,
          "entrant1_score": null,
          "entrant2_score": 0,
          "stage": null,
          "selections": [
            {
              "user_id": 2322500,
              "selection_id": 57498413,
              "character_id": 1331,
              "character_name": "Snake"
            },
            {
              "user_id": 2151157,
              "selection_id": 57498414,
              "character_id": 1339,
              "character_name": "Young Link"
            }
          ]
        }
      ]
    },
    {
      "winner_id": 346254,
      "loser_id": 2166915,
      "winner_score": 2,
      "loser_score": 0,
      "round_text": "Winners Quarter-Final",
      "round": 4,
      "phase": "1",
      "wave": null,
      "dq": false,
      "cancel": false,
      "state": 3,
      "details": [
        {
          "game_id": 38478379,
          "order_num": 1,
          "winner_id": 346254,
          "entrant1_score": null,
          "entrant2_score": 0,
          "stage": "Pokémon Stadium 2",
          "selections": [
            {
              "user_id": 2166915,
              "selection_id": 57498355,
              "character_id": 1335,
              "character_name": "Wario"
            },
            {
              "user_id": 346254,
              "selection_id": 57498356,
              "character_id": 1313,
              "character_name": "Ness"
            }
          ]
        },
        {
          "game_id": 38478380,
          "order_num": 2,
          "winner_id": 346254,
          "entrant1_score": null,
          "entrant2_score": 0,
          "stage": "Small Battlefield",
          "selections": [
            {
              "user_id": 2166915,
              "selection_id": 57498357,
              "character_id": 1335,
              "character_name": "Wario"
            },
            {
              "user_id": 346254,
              "selection_id": 57498358,
              "character_id": 1313,
              "character_name": "Ness"
            }
          ]
        }
      ]
    },
    {
      "winner_id": 2028400,
      "loser_id": 1447017,
      "winner_score": 2,
      "loser_score": 1,
      "round_text": "Winners Quarter-Final",
      "round": 4,
      "phase": "1",
      "wave": null,
      "dq": false,
      "cancel": false,
      "state": 3,
      "details": [
        {
          "game_id": 38478356,
          "order_num": 1,
          "winner_id": 2028400,
          "entrant1_score": null,
          "entrant2_score": 0,
          "stage": null,
          "selections": [
            {
              "user_id": 1447017,
              "selection_id": 57498319,
              "character_id": 1795,
              "character_name": "Pyra & Mythra"
            },
            {
              "user_id": 2028400,
              "selection_id": 57498320,
              "character_id": 1323,
              "character_name": "R.O.B."
            }
          ]
        },
        {
          "game_id": 38478357,
          "order_num": 2,
          "winner_id": 1447017,
          "entrant1_score": 0,
          "entrant2_score": null,
          "stage": null,
          "selections": [
            {
              "user_id": 1447017,
              "selection_id": 57498321,
              "character_id": 1795,
              "character_name": "Pyra & Mythra"
            },
            {
              "user_id": 2028400,
              "selection_id": 57498322,
              "character_id": 1323,
              "character_name": "R.O.B."
            }
          ]
        },
        {
          "game_id": 38478358,
          "order_num": 3,
          "winner_id": 2028400,
          "entrant1_score": null,
          "entrant2_score": 0,
          "stage": null,
          "selections": [
            {
              "user_id": 1447017,
              "selection_id": 57498323,
              "character_id": 1795,
              "character_name": "Pyra & Mythra"
            },
            {
              "user_id": 2028400,
              "selection_id": 57498324,
              "character_id": 1323,
              "character_name": "R.O.B."
            }
          ]
        }
      ]
    },
    {
      "winner_id": 1629776,
      "loser_id": 2166915,
      "winner_score": 2,
      "loser_score": 0,
      "round_text": "Losers Round 5",
      "round": -8,
      "phase": "1",
      "wave": null,
      "dq": false,
      "cancel": false,
      "state": 3,
      "details": []
    },
    {
      "winner_id": 1846904,
      "loser_id": 1447017,
      "winner_score": 2,
      "loser_score": 1,
      "round_text": "Losers Round 5",
      "round": -8,
      "phase": "1",
      "wave": null,
      "dq": false,
      "cancel": false,
      "state": 3,
      "details": []
    },
    {
      "winner_id": 1157521,
      "loser_id": 285335,
      "winner_score": 2,
      "loser_score": 0,
      "round_text": "Losers Round 5",
      "round": -8,
      "phase": "1",
      "wave": null,
      "dq": false,
      "cancel": false,
      "state": 3,
      "details": []
    },
    {
      "winner_id": 1520970,
      "loser_id": 2322500,
      "winner_score": 2,
      "loser_score": 1,
      "round_text": "Losers Round 5",
      "round": -8,
      "phase": "1",
      "wave": null,
      "dq": false,
      "cancel": false,
      "state": 3,
      "details": []
    },
    {
      "winner_id": 1629776,
      "loser_id": 355754,
      "winner_score": 2,
      "loser_score": 0,
      "round_text": "Losers Round 4",
      "round": -7,
      "phase": "1",
      "wave": null,
      "dq": false,
      "cancel": false,
      "state": 3,
      "details": []
    },
    {
      "winner_id": 1846904,
      "loser_id": 387508,
      "winner_score": 2,
      "loser_score": 0,
      "round_text": "Losers Round 4",
      "round": -7,
      "phase": "1",
      "wave": null,
      "dq": false,
      "cancel": false,
      "state": 3,
      "details": []
    },
    {
      "winner_id": 285335,
      "loser_id": 2126685,
      "winner_score": 2,
      "loser_score": 0,
      "round_text": "Losers Round 4",
      "round": -7,
      "phase": "1",
      "wave": null,
      "dq": false,
      "cancel": false,
      "state": 3,
      "details": []
    },
    {
      "winner_id": 1520970,
      "loser_id": 1648405,
      "winner_score": 2,
      "loser_score": 0,
      "round_text": "Losers Round 4",
      "round": -7,
      "phase": "1",
      "wave": null,
      "dq": false,
      "cancel": false,
      "state": 3,
      "details": []
    },
    {
      "winner_id": 134839,
      "loser_id": 1846904,
      "winner_score": 2,
      "loser_score": 1,
      "round_text": "Winners Round 3",
      "round": 3,
      "phase": "1",
      "wave": null,
      "dq": false,
      "cancel": false,
      "state": 3,
      "details": []
    },
    {
      "winner_id": 1157521,
      "loser_id": 387508,
      "winner_score": 2,
      "loser_score": 1,
      "round_text": "Winners Round 3",
      "round": 3,
      "phase": "1",
      "wave": null,
      "dq": false,
      "cancel": false,
      "state": 3,
      "details": [
        {
          "game_id": 38478296,
          "order_num": 1,
          "winner_id": 1157521,
          "entrant1_score": null,
          "entrant2_score": 0,
          "stage": null,
          "selections": [
            {
              "user_id": 1157521,
              "selection_id": 57498204,
              "character_id": 1526,
              "character_name": "Hero"
            },
            {
              "user_id": 387508,
              "selection_id": 57498205,
              "character_id": 1275,
              "character_name": "Cloud"
            }
          ]
        },
        {
          "game_id": 38478297,
          "order_num": 2,
          "winner_id": 387508,
          "entrant1_score": 0,
          "entrant2_score": null,
          "stage": null,
          "selections": [
            {
              "user_id": 387508,
              "selection_id": 57498206,
              "character_id": 1275,
              "character_name": "Cloud"
            },
            {
              "user_id": 1157521,
              "selection_id": 57498207,
              "character_id": 1526,
              "character_name": "Hero"
            }
          ]
        },
        {
          "game_id": 38478306,
          "order_num": 3,
          "winner_id": 1157521,
          "entrant1_score": null,
          "entrant2_score": 0,
          "stage": null,
          "selections": [
            {
              "user_id": 387508,
              "selection_id": 57498224,
              "character_id": 1275,
              "character_name": "Cloud"
            },
            {
              "user_id": 1157521,
              "selection_id": 57498225,
              "character_id": 1526,
              "character_name": "Hero"
            }
          ]
        }
      ]
    },
    {
      "winner_id": 2151157,
      "loser_id": 1637955,
      "winner_score": 2,
      "loser_score": 1,
      "round_text": "Winners Round 3",
      "round": 3,
      "phase": "1",
      "wave": null,
      "dq": false,
      "cancel": false,
      "state": 3,
      "details": []
    },
    {
      "winner_id": 2322500,
      "loser_id": 1393434,
      "winner_score": 2,
      "loser_score": 1,
      "round_text": "Winners Round 3",
      "round": 3,
      "phase": "1",
      "wave": null,
      "dq": false,
      "cancel": false,
      "state": 3,
      "details": [
        {
          "game_id": 38478303,
          "order_num": 1,
          "winner_id": 1393434,
          "entrant1_score": null,
          "entrant2_score": 0,
          "stage": "Pokémon Stadium 2",
          "selections": [
            {
              "user_id": 2322500,
              "selection_id": 57498218,
              "character_id": 1331,
              "character_name": "Snake"
            },
            {
              "user_id": 1393434,
              "selection_id": 57498219,
              "character_id": 1332,
              "character_name": "Sonic"
            }
          ]
        },
        {
          "game_id": 38478304,
          "order_num": 2,
          "winner_id": 2322500,
          "entrant1_score": 0,
          "entrant2_score": null,
          "stage": "Small Battlefield",
          "selections": [
            {
              "user_id": 2322500,
              "selection_id": 57498220,
              "character_id": 1331,
              "character_name": "Snake"
            },
            {
              "user_id": 1393434,
              "selection_id": 57498221,
              "character_id": 1332,
              "character_name": "Sonic"
            }
          ]
        },
        {
          "game_id": 38478305,
          "order_num": 3,
          "winner_id": 2322500,
          "entrant1_score": 0,
          "entrant2_score": null,
          "stage": null,
          "selections": [
            {
              "user_id": 2322500,
              "selection_id": 57498222,
              "character_id": 1331,
              "character_name": "Snake"
            },
            {
              "user_id": 1393434,
              "selection_id": 57498223,
              "character_id": 1332,
              "character_name": "Sonic"
            }
          ]
        }
      ]
    },
    {
      "winner_id": 346254,
      "loser_id": 1648405,
      "winner_score": 2,
      "loser_score": 1,
      "round_text": "Winners Round 3",
      "round": 3,
      "phase": "1",
      "wave": null,
      "dq": false,
      "cancel": false,
      "state": 3,
      "details": []
    },
    {
      "winner_id": 2166915,
      "loser_id": 1520970,
      "winner_score": 2,
      "loser_score": 0,
      "round_text": "Winners Round 3",
      "round": 3,
      "phase": "1",
      "wave": null,
      "dq": false,
      "cancel": false,
      "state": 3,
      "details": []
    },
    {
      "winner_id": 2028400,
      "loser_id": 285335,
      "winner_score": 2,
      "loser_score": 0,
      "round_text": "Winners Round 3",
      "round": 3,
      "phase": "1",
      "wave": null,
      "dq": false,
      "cancel": false,
      "state": 3,
      "details": []
    },
    {
      "winner_id": 1447017,
      "loser_id": 2126685,
      "winner_score": 2,
      "loser_score": 1,
      "round_text": "Winners Round 3",
      "round": 3,
      "phase": "1",
      "wave": null,
      "dq": false,
      "cancel": false,
      "state": 3,
      "details": []
    },
    {
      "winner_id": 355754,
      "loser_id": 1393434,
      "winner_score": 2,
      "loser_score": 1,
      "round_text": "Losers Round 3",
      "round": -6,
      "phase": "1",
      "wave": null,
      "dq": false,
      "cancel": false,
      "state": 3,
      "details": []
    },
    {
      "winner_id": 1629776,
      "loser_id": 1637955,
      "winner_score": 3,
      "loser_score": 0,
      "round_text": "Losers Round 3",
      "round": -6,
      "phase": "1",
      "wave": null,
      "dq": false,
      "cancel": false,
      "state": 3,
      "details": []
    },
    {
      "winner_id": 387508,
      "loser_id": 399533,
      "winner_score": 2,
      "loser_score": 1,
      "round_text": "Losers Round 3",
      "round": -6,
      "phase": "1",
      "wave": null,
      "dq": false,
      "cancel": false,
      "state": 3,
      "details": []
    },
    {
      "winner_id": 1846904,
      "loser_id": 778077,
      "winner_score": 2,
      "loser_score": 0,
      "round_text": "Losers Round 3",
      "round": -6,
      "phase": "1",
      "wave": null,
      "dq": false,
      "cancel": false,
      "state": 3,
      "details": []
    },
    {
      "winner_id": 2126685,
      "loser_id": 1660537,
      "winner_score": 2,
      "loser_score": 1,
      "round_text": "Losers Round 3",
      "round": -6,
      "phase": "1",
      "wave": null,
      "dq": false,
      "cancel": false,
      "state": 3,
      "details": []
    },
    {
      "winner_id": 285335,
      "loser_id": 1530753,
      "winner_score": 2,
      "loser_score": 1,
      "round_text": "Losers Round 3",
      "round": -6,
      "phase": "1",
      "wave": null,
      "dq": false,
      "cancel": false,
      "state": 3,
      "details": []
    },
    {
      "winner_id": 1520970,
      "loser_id": 1949130,
      "winner_score": 2,
      "loser_score": 0,
      "round_text": "Losers Round 3",
      "round": -6,
      "phase": "1",
      "wave": null,
      "dq": false,
      "cancel": false,
      "state": 3,
      "details": []
    },
    {
      "winner_id": 1648405,
      "loser_id": 1913400,
      "winner_score": 2,
      "loser_score": 0,
      "round_text": "Losers Round 3",
      "round": -6,
      "phase": "1",
      "wave": null,
      "dq": false,
      "cancel": false,
      "state": 3,
      "details": []
    },
    {
      "winner_id": 355754,
      "loser_id": 1894370,
      "winner_score": 2,
      "loser_score": 0,
      "round_text": "Losers Round 2",
      "round": -5,
      "phase": "1",
      "wave": null,
      "dq": false,
      "cancel": false,
      "state": 3,
      "details": []
    },
    {
      "winner_id": 1629776,
      "loser_id": 2113509,
      "winner_score": 2,
      "loser_score": 0,
      "round_text": "Losers Round 2",
      "round": -5,
      "phase": "1",
      "wave": null,
      "dq": false,
      "cancel": false,
      "state": 3,
      "details": []
    },
    {
      "winner_id": 399533,
      "loser_id": 1897815,
      "winner_score": 2,
      "loser_score": 0,
      "round_text": "Losers Round 2",
      "round": -5,
      "phase": "1",
      "wave": null,
      "dq": false,
      "cancel": false,
      "state": 3,
      "details": []
    },
    {
      "winner_id": 778077,
      "loser_id": 3134596,
      "winner_score": 2,
      "loser_score": 0,
      "round_text": "Losers Round 2",
      "round": -5,
      "phase": "1",
      "wave": null,
      "dq": false,
      "cancel": false,
      "state": 3,
      "details": []
    },
    {
      "winner_id": 1660537,
      "loser_id": 1469149,
      "winner_score": 2,
      "loser_score": 0,
      "round_text": "Losers Round 2",
      "round": -5,
      "phase": "1",
      "wave": null,
      "dq": false,
      "cancel": false,
      "state": 3,
      "details": []
    },
    {
      "winner_id": 1530753,
      "loser_id": 1343875,
      "winner_score": 2,
      "loser_score": 0,
      "round_text": "Losers Round 2",
      "round": -5,
      "phase": "1",
      "wave": null,
      "dq": false,
      "cancel": false,
      "state": 3,
      "details": []
    },
    {
      "winner_id": 1949130,
      "loser_id": 1846487,
      "winner_score": 2,
      "loser_score": 0,
      "round_text": "Losers Round 2",
      "round": -5,
      "phase": "1",
      "wave": null,
      "dq": false,
      "cancel": false,
      "state": 3,
      "details": []
    },
    {
      "winner_id": 1913400,
      "loser_id": 2646525,
      "winner_score": 2,
      "loser_score": 0,
      "round_text": "Losers Round 2",
      "round": -5,
      "phase": "1",
      "wave": null,
      "dq": false,
      "cancel": false,
      "state": 3,
      "details": []
    },
    {
      "winner_id": 1520970,
      "loser_id": 1897815,
      "winner_score": 2,
      "loser_score": 0,
      "round_text": "Winners Round 2",
      "round": 2,
      "phase": "1",
      "wave": null,
      "dq": false,
      "cancel": false,
      "state": 3,
      "details": []
    },
    {
      "winner_id": 2166915,
      "loser_id": 399533,
      "winner_score": 2,
      "loser_score": 1,
      "round_text": "Winners Round 2",
      "round": 2,
      "phase": "1",
      "wave": null,
      "dq": false,
      "cancel": false,
      "state": 3,
      "details": []
    },
    {
      "winner_id": 285335,
      "loser_id": 1629776,
      "winner_score": 2,
      "loser_score": 0,
      "round_text": "Winners Round 2",
      "round": 2,
      "phase": "1",
      "wave": null,
      "dq": false,
      "cancel": false,
      "state": 3,
      "details": []
    },
    {
      "winner_id": 2028400,
      "loser_id": 2113509,
      "winner_score": 2,
      "loser_score": 1,
      "round_text": "Winners Round 2",
      "round": 2,
      "phase": "1",
      "wave": null,
      "dq": false,
      "cancel": false,
      "state": 3,
      "details": []
    },
    {
      "winner_id": 1447017,
      "loser_id": 1894370,
      "winner_score": 2,
      "loser_score": 1,
      "round_text": "Winners Round 2",
      "round": 2,
      "phase": "1",
      "wave": null,
      "dq": false,
      "cancel": false,
      "state": 3,
      "details": []
    },
    {
      "winner_id": 2126685,
      "loser_id": 355754,
      "winner_score": 2,
      "loser_score": 1,
      "round_text": "Winners Round 2",
      "round": 2,
      "phase": "1",
      "wave": null,
      "dq": false,
      "cancel": false,
      "state": 3,
      "details": []
    },
    {
      "winner_id": 134839,
      "loser_id": 1913400,
      "winner_score": 2,
      "loser_score": 0,
      "round_text": "Winners Round 2",
      "round": 2,
      "phase": "1",
      "wave": null,
      "dq": false,
      "cancel": false,
      "state": 3,
      "details": []
    },
    {
      "winner_id": 1846904,
      "loser_id": 1070709,
      "winner_score": 2,
      "loser_score": 0,
      "round_text": "Winners Round 2",
      "round": 2,
      "phase": "1",
      "wave": null,
      "dq": false,
      "cancel": false,
      "state": 3,
      "details": []
    },
    {
      "winner_id": 1157521,
      "loser_id": 1846487,
      "winner_score": 2,
      "loser_score": 1,
      "round_text": "Winners Round 2",
      "round": 2,
      "phase": "1",
      "wave": null,
      "dq": false,
      "cancel": false,
      "state": 3,
      "details": []
    },
    {
      "winner_id": 387508,
      "loser_id": 2074608,
      "winner_score": 2,
      "loser_score": 0,
      "round_text": "Winners Round 2",
      "round": 2,
      "phase": "1",
      "wave": null,
      "dq": false,
      "cancel": false,
      "state": 3,
      "details": []
    },
    {
      "winner_id": 2151157,
      "loser_id": 1530753,
      "winner_score": 2,
      "loser_score": 0,
      "round_text": "Winners Round 2",
      "round": 2,
      "phase": "1",
      "wave": null,
      "dq": false,
      "cancel": false,
      "state": 3,
      "details": []
    },
    {
      "winner_id": 1637955,
      "loser_id": 1343875,
      "winner_score": 2,
      "loser_score": 0,
      "round_text": "Winners Round 2",
      "round": 2,
      "phase": "1",
      "wave": null,
      "dq": false,
      "cancel": false,
      "state": 3,
      "details": [
        {
          "game_id": 38478289,
          "order_num": 1,
          "winner_id": 1637955,
          "entrant1_score": 0,
          "entrant2_score": null,
          "stage": null,
          "selections": [
            {
              "user_id": 1343875,
              "selection_id": 57498191,
              "character_id": 1405,
              "character_name": "Mr. Game & Watch"
            },
            {
              "user_id": 1637955,
              "selection_id": 57498192,
              "character_id": 1302,
              "character_name": "Mario"
            }
          ]
        },
        {
          "game_id": 38478290,
          "order_num": 2,
          "winner_id": 1637955,
          "entrant1_score": 0,
          "entrant2_score": null,
          "stage": null,
          "selections": [
            {
              "user_id": 1343875,
              "selection_id": 57498193,
              "character_id": 1405,
              "character_name": "Mr. Game & Watch"
            },
            {
              "user_id": 1637955,
              "selection_id": 57498194,
              "character_id": 1302,
              "character_name": "Mario"
            }
          ]
        }
      ]
    },
    {
      "winner_id": 1393434,
      "loser_id": 1660537,
      "winner_score": 2,
      "loser_score": 0,
      "round_text": "Winners Round 2",
      "round": 2,
      "phase": "1",
      "wave": null,
      "dq": false,
      "cancel": false,
      "state": 3,
      "details": []
    },
    {
      "winner_id": 2322500,
      "loser_id": 1635586,
      "winner_score": 2,
      "loser_score": 1,
      "round_text": "Winners Round 2",
      "round": 2,
      "phase": "1",
      "wave": null,
      "dq": false,
      "cancel": false,
      "state": 3,
      "details": []
    },
    {
      "winner_id": 1648405,
      "loser_id": 778077,
      "winner_score": 2,
      "loser_score": 0,
      "round_text": "Winners Round 2",
      "round": 2,
      "phase": "1",
      "wave": null,
      "dq": false,
      "cancel": false,
      "state": 3,
      "details": []
    },
    {
      "winner_id": 346254,
      "loser_id": 3134596,
      "winner_score": 2,
      "loser_score": 0,
      "round_text": "Winners Round 2",
      "round": 2,
      "phase": "1",
      "wave": null,
      "dq": false,
      "cancel": false,
      "state": 3,
      "details": [
        {
          "game_id": 38478294,
          "order_num": 1,
          "winner_id": 346254,
          "entrant1_score": 0,
          "entrant2_score": null,
          "stage": "Small Battlefield",
          "selections": [
            {
              "user_id": 3134596,
              "selection_id": 57498199,
              "character_id": 1290,
              "character_name": "Ice Climbers"
            },
            {
              "user_id": 346254,
              "selection_id": 57498200,
              "character_id": 1313,
              "character_name": "Ness"
            }
          ]
        },
        {
          "game_id": 38478295,
          "order_num": 2,
          "winner_id": 346254,
          "entrant1_score": 0,
          "entrant2_score": null,
          "stage": "Pokémon Stadium 2",
          "selections": [
            {
              "user_id": 3134596,
              "selection_id": 57498201,
              "character_id": 1290,
              "character_name": "Ice Climbers"
            },
            {
              "user_id": 346254,
              "selection_id": 57498202,
              "character_id": 1313,
              "character_name": "Ness"
            }
          ]
        }
      ]
    },
    {
      "winner_id": 355754,
      "loser_id": 1908908,
      "winner_score": 2,
      "loser_score": 1,
      "round_text": "Losers Round 1",
      "round": -4,
      "phase": "1",
      "wave": null,
      "dq": false,
      "cancel": false,
      "state": 3,
      "details": []
    },
    {
      "winner_id": 1894370,
      "loser_id": 3291114,
      "winner_score": 2,
      "loser_score": 0,
      "round_text": "Losers Round 1",
      "round": -4,
      "phase": "1",
      "wave": null,
      "dq": false,
      "cancel": false,
      "state": 3,
      "details": []
    },
    {
      "winner_id": 2113509,
      "loser_id": 1888938,
      "winner_score": 2,
      "loser_score": 1,
      "round_text": "Losers Round 1",
      "round": -4,
      "phase": "1",
      "wave": null,
      "dq": false,
      "cancel": false,
      "state": 3,
      "details": []
    },
    {
      "winner_id": 1629776,
      "loser_id": 1304178,
      "winner_score": 2,
      "loser_score": 0,
      "round_text": "Losers Round 1",
      "round": -4,
      "phase": "1",
      "wave": null,
      "dq": false,
      "cancel": false,
      "state": 3,
      "details": []
    },
    {
      "winner_id": 399533,
      "loser_id": 964573,
      "winner_score": 2,
      "loser_score": 0,
      "round_text": "Losers Round 1",
      "round": -4,
      "phase": "1",
      "wave": null,
      "dq": false,
      "cancel": false,
      "state": 3,
      "details": []
    },
    {
      "winner_id": 1897815,
      "loser_id": 843228,
      "winner_score": 2,
      "loser_score": 0,
      "round_text": "Losers Round 1",
      "round": -4,
      "phase": "1",
      "wave": null,
      "dq": false,
      "cancel": false,
      "state": 3,
      "details": []
    },
    {
      "winner_id": 3134596,
      "loser_id": 1788875,
      "winner_score": 2,
      "loser_score": 0,
      "round_text": "Losers Round 1",
      "round": -4,
      "phase": "1",
      "wave": null,
      "dq": false,
      "cancel": false,
      "state": 3,
      "details": []
    },
    {
      "winner_id": 778077,
      "loser_id": 2099056,
      "winner_score": 2,
      "loser_score": 0,
      "round_text": "Losers Round 1",
      "round": -4,
      "phase": "1",
      "wave": null,
      "dq": false,
      "cancel": false,
      "state": 3,
      "details": []
    },
    {
      "winner_id": 1469149,
      "loser_id": 1635586,
      "winner_score": 2,
      "loser_score": 0,
      "round_text": "Losers Round 1",
      "round": -4,
      "phase": "1",
      "wave": null,
      "dq": false,
      "cancel": false,
      "state": 3,
      "details": []
    },
    {
      "winner_id": 1660537,
      "loser_id": 795805,
      "winner_score": 2,
      "loser_score": 0,
      "round_text": "Losers Round 1",
      "round": -4,
      "phase": "1",
      "wave": null,
      "dq": false,
      "cancel": false,
      "state": 3,
      "details": []
    },
    {
      "winner_id": 1343875,
      "loser_id": 550435,
      "winner_score": 2,
      "loser_score": 0,
      "round_text": "Losers Round 1",
      "round": -4,
      "phase": "1",
      "wave": null,
      "dq": false,
      "cancel": false,
      "state": 3,
      "details": []
    },
    {
      "winner_id": 1530753,
      "loser_id": 23654,
      "winner_score": 2,
      "loser_score": 1,
      "round_text": "Losers Round 1",
      "round": -4,
      "phase": "1",
      "wave": null,
      "dq": false,
      "cancel": false,
      "state": 3,
      "details": []
    },
    {
      "winner_id": 1949130,
      "loser_id": 2074608,
      "winner_score": 2,
      "loser_score": 1,
      "round_text": "Losers Round 1",
      "round": -4,
      "phase": "1",
      "wave": null,
      "dq": false,
      "cancel": false,
      "state": 3,
      "details": []
    },
    {
      "winner_id": 1846487,
      "loser_id": 1604268,
      "winner_score": 2,
      "loser_score": 1,
      "round_text": "Losers Round 1",
      "round": -4,
      "phase": "1",
      "wave": null,
      "dq": false,
      "cancel": false,
      "state": 3,
      "details": []
    },
    {
      "winner_id": 2646525,
      "loser_id": 1070709,
      "winner_score": 2,
      "loser_score": 0,
      "round_text": "Losers Round 1",
      "round": -4,
      "phase": "1",
      "wave": null,
      "dq": false,
      "cancel": false,
      "state": 3,
      "details": []
    },
    {
      "winner_id": 1913400,
      "loser_id": 2608066,
      "winner_score": 2,
      "loser_score": 0,
      "round_text": "Losers Round 1",
      "round": -4,
      "phase": "1",
      "wave": null,
      "dq": false,
      "cancel": false,
      "state": 3,
      "details": []
    },
    {
      "winner_id": 1913400,
      "loser_id": 1908908,
      "winner_score": 2,
      "loser_score": 0,
      "round_text": "Winners Round 1",
      "round": 1,
      "phase": "1",
      "wave": null,
      "dq": false,
      "cancel": false,
      "state": 3,
      "details": []
    },
    {
      "winner_id": 1070709,
      "loser_id": 3291114,
      "winner_score": 2,
      "loser_score": 0,
      "round_text": "Winners Round 1",
      "round": 1,
      "phase": "1",
      "wave": null,
      "dq": false,
      "cancel": false,
      "state": 3,
      "details": []
    },
    {
      "winner_id": 1846487,
      "loser_id": 1888938,
      "winner_score": 2,
      "loser_score": 0,
      "round_text": "Winners Round 1",
      "round": 1,
      "phase": "1",
      "wave": null,
      "dq": false,
      "cancel": false,
      "state": 3,
      "details": []
    },
    {
      "winner_id": 2074608,
      "loser_id": 1304178,
      "winner_score": 2,
      "loser_score": 0,
      "round_text": "Winners Round 1",
      "round": 1,
      "phase": "1",
      "wave": null,
      "dq": false,
      "cancel": false,
      "state": 3,
      "details": []
    },
    {
      "winner_id": 1530753,
      "loser_id": 964573,
      "winner_score": 2,
      "loser_score": 1,
      "round_text": "Winners Round 1",
      "round": 1,
      "phase": "1",
      "wave": null,
      "dq": false,
      "cancel": false,
      "state": 3,
      "details": []
    },
    {
      "winner_id": 1637955,
      "loser_id": 843228,
      "winner_score": 2,
      "loser_score": 0,
      "round_text": "Winners Round 1",
      "round": 1,
      "phase": "1",
      "wave": null,
      "dq": false,
      "cancel": false,
      "state": 3,
      "details": []
    },
    {
      "winner_id": 1660537,
      "loser_id": 1788875,
      "winner_score": 2,
      "loser_score": 0,
      "round_text": "Winners Round 1",
      "round": 1,
      "phase": "1",
      "wave": null,
      "dq": false,
      "cancel": false,
      "state": 3,
      "details": []
    },
    {
      "winner_id": 1635586,
      "loser_id": 2099056,
      "winner_score": 2,
      "loser_score": 0,
      "round_text": "Winners Round 1",
      "round": 1,
      "phase": "1",
      "wave": null,
      "dq": false,
      "cancel": false,
      "state": 3,
      "details": []
    },
    {
      "winner_id": 778077,
      "loser_id": 1469149,
      "winner_score": 2,
      "loser_score": 0,
      "round_text": "Winners Round 1",
      "round": 1,
      "phase": "1",
      "wave": null,
      "dq": false,
      "cancel": false,
      "state": 3,
      "details": []
    },
    {
      "winner_id": 346254,
      "loser_id": 795805,
      "winner_score": 2,
      "loser_score": 0,
      "round_text": "Winners Round 1",
      "round": 1,
      "phase": "1",
      "wave": null,
      "dq": false,
      "cancel": false,
      "state": 3,
      "details": []
    },
    {
      "winner_id": 1897815,
      "loser_id": 550435,
      "winner_score": 2,
      "loser_score": 0,
      "round_text": "Winners Round 1",
      "round": 1,
      "phase": "1",
      "wave": null,
      "dq": false,
      "cancel": false,
      "state": 3,
      "details": []
    },
    {
      "winner_id": 2166915,
      "loser_id": 23654,
      "winner_score": 2,
      "loser_score": 1,
      "round_text": "Winners Round 1",
      "round": 1,
      "phase": "1",
      "wave": null,
      "dq": false,
      "cancel": false,
      "state": 3,
      "details": []
    },
    {
      "winner_id": 1629776,
      "loser_id": 1949130,
      "winner_score": 2,
      "loser_score": 0,
      "round_text": "Winners Round 1",
      "round": 1,
      "phase": "1",
      "wave": null,
      "dq": false,
      "cancel": false,
      "state": 3,
      "details": []
    },
    {
      "winner_id": 2113509,
      "loser_id": 1604268,
      "winner_score": 2,
      "loser_score": 0,
      "round_text": "Winners Round 1",
      "round": 1,
      "phase": "1",
      "wave": null,
      "dq": false,
      "cancel": false,
      "state": 3,
      "details": []
    },
    {
      "winner_id": 1894370,
      "loser_id": 2646525,
      "winner_score": 2,
      "loser_score": 0,
      "round_text": "Winners Round 1",
      "round": 1,
      "phase": "1",
      "wave": null,
      "dq": false,
      "cancel": false,
      "state": 3,
      "details": []
    },
    {
      "winner_id": 2126685,
      "loser_id": 2608066,
      "winner_score": 2,
      "loser_score": 0,
      "round_text": "Winners Round 1",
      "round": 1,
      "phase": "1",
      "wave": null,
      "dq": false,
      "cancel": false,
      "state": 3,
      "details": []
    }
  ],
  "version": "1.0"
}